{
    "domain": "algolia.net",
    "owner": {
        "name": "Algolia Inc",
        "displayName": "Algolia"
    },
    "source": [
        "DuckDuckGo-US"
    ],
    "prevalence": 0.0028,
    "sites": 411,
    "subdomains": [
        "bonwjfmmrs-dsn",
        "cy6dj1risq-dsn",
        "68aonza1g5-dsn",
        "y2y10mz7jy-dsn",
        "x9n0adam9m-dsn",
        "qjc9mizn9s-dsn",
        "2qwlvlxzb6-dsn",
        "fnt00qyklt-dsn",
        "ofcncog2cu-dsn",
        "ic23zxnzkt-dsn",
        "73vku7tj5x-dsn",
        "bx6xcc9gxo-dsn",
        "4dqkrasvv8-dsn",
        "07wo0u62k9-dsn",
        "i2uwp1cwqx-dsn",
        "lvec6jr2og-dsn",
        "tugz383si1-dsn",
        "6545wu9pd4-dsn",
        "manee605r4-dsn",
        "q9lc2gea1o-dsn",
        "gaf8a9agvn-dsn",
        "9covf8wtlv-dsn",
        "5ddt8ji69m-dsn",
        "n95emuhkii-dsn",
        "eq79xlpiu7-dsn",
        "hanur59r57-dsn",
        "9nhgaoxpjg-dsn",
        "4a5n71xyh0-dsn",
        "7lvr1jktdf-dsn",
        "7urolr2xk0-dsn",
        "hz5km6p7b5-dsn",
        "ub7td8aizc-dsn",
        "xa10ukg343-dsn",
        "djjfeekfkz-dsn",
        "jgrxrfvqm0-dsn",
        "m58222sh95-dsn",
        "5lselcfmiw-dsn",
        "8etu77zv14-dsn",
        "b19l7w540a-dsn",
        "be42cuc5go-dsn",
        "m5oigtw601-dsn",
        "0qhqe3pguj-dsn",
        "pn9qilhu0v-dsn",
        "1h42bjpl1u-dsn",
        "ouhnfvb7wy-dsn",
        "4v9py0nong-dsn",
        "hwpwewotf5-dsn",
        "ogg7av1jsp-dsn",
        "wqd8kyms9k-dsn",
        "gb3bhh57fj-dsn",
        "xely3u4lod-dsn",
        "u3c1ptpi5o-dsn",
        "93vtyj8vuk-dsn",
        "vfoof4g2cg-dsn",
        "6x6rkba85v-dsn",
        "02axj3t77t-dsn",
        "cv2vlubkg6-dsn",
        "bh4d9od16a-dsn",
        "1ngizu78ob-dsn",
        "p2mlbkgfds-dsn",
        "mra2hn75it-dsn",
        "t5qjjs38p2-dsn",
        "dirgdxwm7t-dsn",
        "wp8q3hdhdz-dsn",
        "7xxlgnqrtz-dsn",
        "uqr5x9aud4-dsn",
        "uok6vs5ov2-dsn",
        "0t5cr44pkn-dsn",
        "tsmkfa364q-dsn",
        "07g6lsohsq-dsn",
        "qx5ips1b1q-dsn",
        "9ioacg5nhe-dsn",
        "y1fnzxui30-dsn",
        "p3kygekdme-dsn",
        "r8fbfl7x8d-dsn",
        "bzshv0ttwo-dsn",
        "mm26bpdw6v-dsn",
        "rftod1k2s3-dsn",
        "9vmz5hxzr0-dsn",
        "ir09eo50x5-dsn",
        "6eh1ib012d-dsn",
        "g6qbk0086l-dsn",
        "drp4o45g5t-dsn",
        "51jza0jb8u-dsn",
        "eogj4bjfa8-dsn",
        "ijaxo422tu-dsn",
        "9rchu62dop-dsn",
        "h5yovykinu-dsn",
        "f12a8sordm-dsn",
        "escht2hh74-dsn",
        "cu5a135pq9-dsn",
        "hsgrv0nid9-dsn",
        "dkvugqjm5c-dsn",
        "6z1x4vph2b-dsn",
        "sswu34x67q-dsn",
        "tfg47vtipm-dsn",
        "lua9b20g37-dsn",
        "ubvy2tkvkb-dsn",
        "22mg8hzkho-dsn",
        "3mudfzohw9-dsn",
        "bisgn0tc5b-dsn",
        "xxh6l2io6p-dsn",
        "th8ix1g260-dsn",
        "kpmi3ddnef-dsn",
        "zogf71lkch-dsn",
        "fy8plebn34-dsn",
        "cgrd9wlxe4-dsn",
        "w2m9492ddv-dsn",
        "xn5vepvd4i-dsn",
        "ii1tgvjxdc-dsn",
        "43kmjyqoga-dsn",
        "0mool54xjv-dsn",
        "bc4sa39fg5-dsn",
        "txmwq920bd-dsn",
        "1gth8h5lzo-dsn",
        "ngmhtyxt0t-dsn",
        "8hwbow9b9m-dsn",
        "mnrwefss2q-dsn",
        "ckpamvuube-dsn",
        "b5iu9lvsk0-dsn",
        "nsumzflkaw-dsn",
        "icjv6bx83y-dsn",
        "0iz6gtnjfs-dsn",
        "mf71907vrc-dsn",
        "qvwwc7jv7a-dsn",
        "9tyf7rjuhq-dsn",
        "34t7ohog1z-dsn",
        "125asmte6f-dsn",
        "vfm4x0n23a-dsn",
        "xmz6r0zru0-dsn",
        "msn7pvpzhu-dsn",
        "my37rxskcd-dsn",
        "vtvkm5urpx-dsn",
        "pczym1qrdw-dsn",
        "0n798ugd65-dsn",
        "c738agbp0j-dsn",
        "4k4zn64x03-dsn",
        "p03j33bea0-dsn",
        "p28kr2j94g-dsn",
        "ulrh5gm865-dsn",
        "fd1a5vmjfk-dsn",
        "70h8cy4zee-dsn",
        "mes124x9ka-dsn",
        "ujjak2x1py-dsn",
        "junr3sucf2-dsn",
        "y0oirxd0rf-dsn",
        "y72zzu5ph1-dsn",
        "pa6v8u79h6-dsn",
        "1g1t9vu97f-dsn",
        "ai1nanacyd-dsn",
        "rhpot4rjo4-dsn",
        "2ibg7p8tz0-dsn",
        "uwxbmb9os2-dsn",
        "tab7nw1g4p-dsn",
        "f1cgl758bn-dsn",
        "7msii23cds-dsn",
        "k535caawve-dsn",
        "ml35qlwpoc-dsn",
        "nj4qx1mfj2-dsn",
        "cmt67e9hpx-dsn",
        "xfl0ypvnpc-dsn",
        "lmmq6oh1aa-dsn",
        "xfoi9ebbhr-dsn",
        "day79mubw3-dsn",
        "f49rvkeckz-dsn",
        "acp1l90vbv-dsn",
        "i92a5jeatg-dsn",
        "sgpwkwy6ld-dsn",
        "nhehr8xbao-dsn",
        "ampaw8yccp-dsn",
        "eyaffs0rc4-dsn",
        "nyg9olhwjb-dsn",
        "fuin3o4lcf-dsn",
        "wy1ijurp9u-dsn",
        "lkay4pjwx5-dsn",
        "eydbvk6xrl-dsn",
        "5g2ejzroxz-dsn",
        "yu04vo4tup-dsn",
        "1smt7i1wqy-dsn",
        "fa677j9qji-dsn",
        "xil6vmff24-dsn",
        "zvix9dzogt-dsn",
        "kr0ysyytjt-dsn",
        "o28sy4q7wu-dsn",
        "dy1fhernj8-dsn",
        "hvos52jiuu-dsn",
        "od48yheotk-dsn",
        "2125ht9m59-dsn",
        "ysu8j82bmw-dsn",
        "ookh1nfe65-dsn",
        "vvhhpetr0v-dsn",
        "m6kwpq0qr9-dsn",
        "ha37j7jvqs-dsn",
        "1hwjvf93zd-dsn",
        "za0wtrqofi-dsn",
        "vkd6qvboxd-dsn",
        "zsujlf71ok-dsn",
        "avcvysejs1-dsn",
        "gbsjcb48tj-dsn",
        "mb13iy345y-dsn",
        "5g12g3w07f-dsn",
        "biaszb3pro-dsn",
        "nwwdd82a89-dsn",
        "h4j3sto8lt-dsn",
        "7dw9doo8qk-dsn",
        "3x73s963e7-dsn",
        "hzoxaduqy8-dsn",
        "02ds8korfw-dsn",
        "xo4u4y7c0t-dsn",
        "n055sbtiwt-dsn",
        "okzyi6r8r8-dsn",
        "rcyz6lcx38-dsn",
        "qjaugn1pvu-dsn",
        "m8ujg2x7hl-dsn",
        "kgun8faipf-dsn",
        "42pgxxd20k-dsn",
        "3q37gxuu9i-dsn",
        "drnz5p2ski-dsn",
        "04ie0383at-dsn",
        "3g3t2s1ucd-dsn",
        "zxbjr4u3np-dsn",
        "5vuajpxyrn-dsn",
        "pxa5v6axkq-dsn",
        "zfdm04fn4z-dsn",
        "cfaxieb3i5-dsn",
        "nzylatfz2q-dsn",
        "ok42bx2aqd-dsn",
        "6m60w1zkr5-dsn",
        "ssdqwuevb6-dsn",
        "zbpf4p5c1e-dsn",
        "ubqp4aes36-dsn",
        "i4melyi9o9-dsn",
        "668rb43gd4-dsn",
        "yg3l958nut-dsn",
        "j8n8i8ke2y-dsn",
        "flwdn2189e-dsn",
        "vbt275cjrz-dsn",
        "j5nefinov3-dsn",
        "bcxurw325t-dsn",
        "u5s8kv3uw0-dsn"
    ],
    "cnames": [],
    "fingerprinting": 0,
    "resources": [
        {
            "rule": "algolia\\.net\\/1\\/indexes\\/*\\/queries",
            "cookies": 0,
            "fingerprinting": 0,
            "subdomains": [
                "bonwjfmmrs-dsn",
                "cy6dj1risq-dsn",
                "68aonza1g5-dsn",
                "y2y10mz7jy-dsn",
                "x9n0adam9m-dsn",
                "qjc9mizn9s-dsn",
                "2qwlvlxzb6-dsn",
                "fnt00qyklt-dsn",
                "ofcncog2cu-dsn",
                "ic23zxnzkt-dsn",
                "73vku7tj5x-dsn",
                "bx6xcc9gxo-dsn",
                "4dqkrasvv8-dsn",
                "07wo0u62k9-dsn",
                "i2uwp1cwqx-dsn",
                "lvec6jr2og-dsn",
                "tugz383si1-dsn",
                "6545wu9pd4-dsn",
                "manee605r4-dsn",
                "q9lc2gea1o-dsn",
                "gaf8a9agvn-dsn",
                "9covf8wtlv-dsn",
                "5ddt8ji69m-dsn",
                "n95emuhkii-dsn",
                "eq79xlpiu7-dsn",
                "hanur59r57-dsn",
                "9nhgaoxpjg-dsn",
                "4a5n71xyh0-dsn",
                "7lvr1jktdf-dsn",
                "7urolr2xk0-dsn",
                "hz5km6p7b5-dsn",
                "ub7td8aizc-dsn",
                "xa10ukg343-dsn",
                "djjfeekfkz-dsn",
                "jgrxrfvqm0-dsn",
                "m58222sh95-dsn",
                "5lselcfmiw-dsn",
                "8etu77zv14-dsn",
                "b19l7w540a-dsn",
                "be42cuc5go-dsn",
                "m5oigtw601-dsn",
                "0qhqe3pguj-dsn",
                "pn9qilhu0v-dsn",
                "1h42bjpl1u-dsn",
                "ouhnfvb7wy-dsn",
                "4v9py0nong-dsn",
                "hwpwewotf5-dsn",
                "ogg7av1jsp-dsn",
                "wqd8kyms9k-dsn",
                "gb3bhh57fj-dsn",
                "xely3u4lod-dsn",
                "u3c1ptpi5o-dsn",
                "93vtyj8vuk-dsn",
                "vfoof4g2cg-dsn",
                "6x6rkba85v-dsn",
                "02axj3t77t-dsn",
                "cv2vlubkg6-dsn",
                "bh4d9od16a-dsn",
                "1ngizu78ob-dsn",
                "p2mlbkgfds-dsn",
                "mra2hn75it-dsn",
                "t5qjjs38p2-dsn",
                "dirgdxwm7t-dsn",
                "wp8q3hdhdz-dsn",
                "7xxlgnqrtz-dsn",
                "uqr5x9aud4-dsn",
                "uok6vs5ov2-dsn",
                "0t5cr44pkn-dsn",
                "tsmkfa364q-dsn",
                "07g6lsohsq-dsn",
                "qx5ips1b1q-dsn",
                "9ioacg5nhe-dsn",
                "y1fnzxui30-dsn",
                "p3kygekdme-dsn",
                "r8fbfl7x8d-dsn",
                "bzshv0ttwo-dsn",
                "mm26bpdw6v-dsn",
                "rftod1k2s3-dsn",
                "9vmz5hxzr0-dsn",
                "ir09eo50x5-dsn",
                "6eh1ib012d-dsn",
                "g6qbk0086l-dsn",
                "drp4o45g5t-dsn",
                "51jza0jb8u-dsn",
                "eogj4bjfa8-dsn",
                "ijaxo422tu-dsn",
                "9rchu62dop-dsn",
                "h5yovykinu-dsn",
                "f12a8sordm-dsn",
                "escht2hh74-dsn",
                "cu5a135pq9-dsn",
                "hsgrv0nid9-dsn",
                "dkvugqjm5c-dsn",
                "6z1x4vph2b-dsn",
                "sswu34x67q-dsn",
                "tfg47vtipm-dsn",
                "lua9b20g37-dsn",
                "ubvy2tkvkb-dsn",
                "22mg8hzkho-dsn",
                "3mudfzohw9-dsn",
                "bisgn0tc5b-dsn",
                "xxh6l2io6p-dsn",
                "th8ix1g260-dsn",
                "kpmi3ddnef-dsn",
                "zogf71lkch-dsn",
                "fy8plebn34-dsn",
                "cgrd9wlxe4-dsn",
                "w2m9492ddv-dsn",
                "xn5vepvd4i-dsn",
                "ii1tgvjxdc-dsn",
                "43kmjyqoga-dsn",
                "0mool54xjv-dsn",
                "bc4sa39fg5-dsn",
                "txmwq920bd-dsn",
                "1gth8h5lzo-dsn",
                "ngmhtyxt0t-dsn",
                "8hwbow9b9m-dsn",
                "mnrwefss2q-dsn",
                "ckpamvuube-dsn",
                "b5iu9lvsk0-dsn",
                "nsumzflkaw-dsn",
                "icjv6bx83y-dsn",
                "0iz6gtnjfs-dsn",
                "mf71907vrc-dsn",
                "qvwwc7jv7a-dsn",
                "9tyf7rjuhq-dsn",
                "34t7ohog1z-dsn",
                "125asmte6f-dsn",
                "vfm4x0n23a-dsn",
                "xmz6r0zru0-dsn",
                "msn7pvpzhu-dsn",
                "my37rxskcd-dsn",
                "vtvkm5urpx-dsn",
                "pczym1qrdw-dsn",
                "0n798ugd65-dsn",
                "c738agbp0j-dsn",
                "4k4zn64x03-dsn",
                "p03j33bea0-dsn",
                "p28kr2j94g-dsn",
                "ulrh5gm865-dsn",
                "fd1a5vmjfk-dsn",
                "70h8cy4zee-dsn",
                "mes124x9ka-dsn",
                "ujjak2x1py-dsn",
                "junr3sucf2-dsn",
                "y0oirxd0rf-dsn",
                "y72zzu5ph1-dsn",
                "pa6v8u79h6-dsn",
                "1g1t9vu97f-dsn",
                "ai1nanacyd-dsn",
                "rhpot4rjo4-dsn",
                "2ibg7p8tz0-dsn",
                "uwxbmb9os2-dsn",
                "tab7nw1g4p-dsn",
                "f1cgl758bn-dsn",
                "7msii23cds-dsn",
                "k535caawve-dsn",
                "ml35qlwpoc-dsn",
                "nj4qx1mfj2-dsn",
                "cmt67e9hpx-dsn",
                "xfl0ypvnpc-dsn",
                "lmmq6oh1aa-dsn",
                "xfoi9ebbhr-dsn",
                "day79mubw3-dsn",
                "f49rvkeckz-dsn",
                "acp1l90vbv-dsn",
                "i92a5jeatg-dsn",
                "sgpwkwy6ld-dsn",
                "nhehr8xbao-dsn",
                "ampaw8yccp-dsn",
                "eyaffs0rc4-dsn",
                "nyg9olhwjb-dsn",
                "fuin3o4lcf-dsn",
                "wy1ijurp9u-dsn",
                "lkay4pjwx5-dsn",
                "eydbvk6xrl-dsn",
                "5g2ejzroxz-dsn",
                "yu04vo4tup-dsn",
                "1smt7i1wqy-dsn",
                "fa677j9qji-dsn",
                "xil6vmff24-dsn",
                "zvix9dzogt-dsn",
                "kr0ysyytjt-dsn",
                "o28sy4q7wu-dsn",
                "dy1fhernj8-dsn",
                "hvos52jiuu-dsn",
                "od48yheotk-dsn",
                "2125ht9m59-dsn",
                "ysu8j82bmw-dsn",
                "ookh1nfe65-dsn",
                "vvhhpetr0v-dsn",
                "m6kwpq0qr9-dsn",
                "ha37j7jvqs-dsn",
                "1hwjvf93zd-dsn",
                "za0wtrqofi-dsn",
                "vkd6qvboxd-dsn",
                "zsujlf71ok-dsn",
                "avcvysejs1-dsn",
                "gbsjcb48tj-dsn",
                "mb13iy345y-dsn",
                "5g12g3w07f-dsn",
                "biaszb3pro-dsn",
                "nwwdd82a89-dsn",
                "h4j3sto8lt-dsn",
                "7dw9doo8qk-dsn",
                "3x73s963e7-dsn",
                "hzoxaduqy8-dsn",
                "02ds8korfw-dsn",
                "xo4u4y7c0t-dsn",
                "n055sbtiwt-dsn",
                "okzyi6r8r8-dsn",
                "rcyz6lcx38-dsn",
                "qjaugn1pvu-dsn",
                "m8ujg2x7hl-dsn"
            ],
            "apis": {},
            "sites": 261,
            "prevalence": 0.00178,
            "cnames": [],
            "responseHashes": [
                "6003456f7c3e2f7c9b15cc2a1f8e8e3bc3b05dd439de6bd4dda34527270bbaae",
                "1c68f3b0ba11bbd664db99ba0e8709aa5df486a88eb5aa116e3dad74f7b765e8",
                "941a1003d5a59b8c0dd3548664b8f09f6003e0220c57865eb59c9e81973084b9",
                "d02b0eb64afa212d203c141113a5537bec26ff0aa6cc13c488f6e560fa038546",
                "b80b19c84ff1d78c5ee07805de7c13ec44ffb55416f47b3193d69dd9920c4c5f",
                "159e5eb3a87cef19505380ab8b0e4675ece2d50749fa49fb5c455bbb3e424c33",
                "8afe594782260bbb1d3df905e9950190f5bd3756ad2587d8bb5195c9e852c58d",
                "43bef87a9cc9ea321fb6578358a7a716e877ce97a3aa98f54679eaf676fd1b74",
                "d4102d51813c51d636f3fd560ce7bcffabb29d726c41463e58d41c9d15b8d2bf",
                "c4f16dee1871c48985c825cf09ceffbd56ca74063df9acf94a3ddd0bce67ab98",
                "1bd528e22e03152e9479e86aad89eb3996b2d126055560c1819ad56db3e6a113",
                "ef516e50a82a8e30c0e9e486abfcac9f4a63e257fbfc5a01b4bd06464f0015a1",
                "3fefff1a75a0ee16af0f659555c94f262ccee52d5abb5f788746c4b434554d77",
                "0b47817fcf0037d17798c409424b9e41c2c51dd56da1f7b32e3a8649ad43fa55",
                "399aae32db650a8895838775c2f30f437945ee630150bbc2cf045f1ab5aba321",
                "5f3ae84161ff015db753229f9fa5e0a08387b0ecb290818a11fde18a59a4497c",
                "93f467d6b23d5ebbdff2825ac78212f06622e72893b69aa93d9709ed3a07254e",
                "157030047d8480216977bf477941e8297add3a4490d9b22a37526e4eacee74f7",
                "b5764e726e21cccf41e644806916f6f92427b02bc73e4d258970c754fb9617c6",
                "f8a73b994358715fcf3aabf1cda11a295431ad6ad199c3eda60c4cc59d51736b",
                "4d5f74a1c7e46dee3cb1277f597477313378685237553f1be815d2093b373738",
                "ed5cb6b824179705fb84eafcb4a4da90cd8a01e83d736f62cd08938f68f7898f",
                "ba5c0e287c34d5d5839c9d7dad286a34de688447f3bc3a21297c7a2f4c81f162",
                "914635bcd3ed7e1d9aebf3865cd090161fec5ac28947f1239d690ba6ee6c8266",
                "98157c6cbeea5c8e2313783ef8059c7c4edc28cde2b6fe9f66f3ad6ccfab7525",
                "22743f9a4abc399c8e9988721feda490071c4be6b16ab0897285e6ffaf06b71e",
                "d02085e61b193556fd4ae818eff36ec11179a51b61ade1a00a129ea2bf6ef300",
                "859fbf6ae11821b5236dbd3a6bb3bab749eab94ee8263f2533617886f87ce9dc",
                "5bc0dbb5840cbfc785a5c7e8e4e3c3405a8b887832d2254aec9a89307656c200",
                "ab205f419000c85faf76eb37a1e14b1caa8d53346dfae67c76d45250dc2183a2",
                "9f39768ae6e9708d0cfbfab0b809030aee0008df0ce13ff997dfca11dcaba533",
                "5b481f1dbb968138151b65ce89bd0b071bc755418938feb9435de7a9bb64c9ab",
                "b888088ed1b126b97b003d62ced2c10d683e42b65d5d12ff5102eae7a67f5699",
                "4683204a2528facc9cbaad428e2ae0b309b89fe5879109322c1356fd580d86ec",
                "867ba1e17fd87510eaa452ae091073ec6f7dfcb66acbf4cfb6419231dc0827c1",
                "f6f9f777a46fadbebe4a8378fdc8b9e4ad9b09e89f981201eb405c32a481b350",
                "c59bf5c90baed89e97ffe61d545cbaa3973e5ba1b836f50de6e7fd8ccaf09255",
                "9b21dca05772fb3ad7e09d2896ead669d5a931c068d306576a68c7a2e9238464",
                "4193f9990af74d685fd93319f50052ded2279af0f14211dff0a9018c5ec2e6b3",
                "8b8c207f945a605e80fc9110cdc97536425205e7e28e77c68be59ab3197ba379",
                "dc1637f370d2d549448b5a19979ace2aa8ce9eb1235616c3b643597b626195a8",
                "7186edce763d4c01458c164df6a0e8292237fb1a05f37d8580c8bb10ea31d010",
                "6a79567ad9aec80fcbde6f7d4bcc5998ba882ac65aed4ea0a3d29c840cff86ba",
                "847e527693fb77d1b23e68cf02942fc8f85417f5045eb4b29c598c9297cd10a1",
                "9b9cfe90a30790e38d9f8b47e9d63017401e93ac3044ea680f3a26697387a457",
                "2197d7522b45f7e78476703c53a18f7f5faf886e7b23ef151de7198b4fe4dab7",
                "5a7287548106f2f9a23d282623e21f6d3c7a0cad6ae4a20697904331c8e3fa5f",
                "60197c58315c3f0788200861f20862413d2473d90c10e2df723962fb82005861",
                "6137f99755d1529958d1d67e69a4d3532855e7f24baad8523aab224516f0a8cc",
                "058d32537417eea1c299bf3e3c8e159c566cf84bc76031f927149f05e0930284",
                "70e30c0637e16f191d1e6445aad421d82331b59e15bb6fdf7e920570353c0851",
                "c076152afc13589703f667cc56168e65418e1cde3001af1fc92d1dbf5eefae12",
                "6fc5fdb176e36a3307d481d82414c584c1adceb06b40fe3620aa1a43fc8720a8",
                "6fbf4824362843e47dbd9176ea98cb900815b331351f6faa455551a9cbab317d",
                "0430908c7437b2b6f9277a66cd3d6e0031761b3617ee5c7e77b3b986fae64c0b",
                "98eab78d742c852f6c69b6b38ba31ff302f024471a511cb377d9c3cf3331da60",
                "10b06c69782f055d8878eaef57b7b884fa95419de460ea32dca7ace3ae4ea620",
                "eae22d06b483f2ae6344a5ec9dcc8513c644c24ba98b9e1db22dc4983d3f6a6c",
                "8f80aac387c351803b78948f6a4778a300a4e86055ab814ab151fd4ca97c4f63",
                "4d0f7206254f8340e4bc71a3c36feaf0ec7edbaeea5ed0406448ea17ea92a266",
                "7ff7b636a6d082db27d3d57cf2067185663d04d342b62dd30794eb7f56488a7e",
                "bbd2d1cc6a348a957d5ad816ca932da4d3950c4bea144e77f140e3175048fa22",
                "5326e917fb1b3108dfa883556bfa555e265ee2a1cb05aa96722ec2880a72e3a3",
                "df0af04c0a88acc15b2b1677cd06f0017c1e7623e8b931e7c1562cd920200b6d",
                "8d319bd784af45988726c73defcaf4964ceddd97902ec60547bc12b67c17fb13",
                "8aa7f1637a4632e14bad387c9b3c75589c94d9fadd244435ed7a5de11427d57c",
                "831e1e6ba46cb0b34958c1bbe77ff7af6419daf23bed84c8e88b98e9041b3a4b",
                "0755a3179ab61df195a46f7b2ae682d6c875ba99ebeb0b8e162dda24830f09f3",
                "c4120868c79309fac5ee52f2c0298a385b1372b930a8cdb6b555b6e96924aed5",
                "f051a6af90e4bcaf710294e74e46963600944e047e0899bb21cc0bd196d10a8d",
                "d39166ce0317cdc80fb40fc2cfe97a7abba0a6608537221494a5939b24e5a19c",
                "ed1c3cb60ed0a32166a160a8b0f549d4b833e29add0a1cfc1e9d2c79652e1a12",
                "26c0fc44d6290fc24343c66f72fde3e89059554bed7b951878a152fe6a26b4bf",
                "92d48e39a41885a3ccbc5c1a26ba67c9558a181c8116ad8c8de399fbd7140f8a",
                "9b2ec87290b2ca99d0b69ba7e9a2403dd57c1c8a37231daca9cc6da80b34822e",
                "e62423bf2fe5d2c41e065fef576491a415deb6e070f0646a8edb7817cbf9cc53",
                "a0d953a59db16399d0d6b595041d751b09f351ee3a949bfa0d5c10db135907a8",
                "8aeef5ca1d6bb826717aed02c36501a1abfe0e1017a25f26a77d31757e4f090c",
                "bc4e3f421b5f2408a3ebbaea2b624d07f0f4df5342d295abe1aca70f34e991a0",
                "b246cbd8db7f88b6f564f4109206571ab319f13de5a99b51e287e7b5612edf6c",
                "780a9f90ea0a3300721d0e273268cf6b5100e6f46f8890c926ed355faca944b6",
                "6b4858af6419362c1c32bbfa85d3cd4bb50c1966caba08086fc65583be429468",
                "0ca9e36f8e4aba0323d447484bdc62849aa898ab023eb92cedd44435937bcc3c",
                "2d539d4663cf88f500517021fe5f3ec3c5b756616e10c6a6166eee2e5c1b9730",
                "5ccaab430115caf3f337673030bd9fb282dee3a19ac349df388e953ed7ce3f05",
                "5cd9c87d3df05b3dbf40f8b9431d53674869b3ab9223a091c11430b022409a92",
                "e74ce7a752b0a09dc948a3768accde810b675e9bb59b580e1dad4c19ed308f93",
                "143a8be1525b394c0fb9be6136076646186f0c3604ea15a88b40adc0688b1720",
                "d6ee127a076442054f957d1e4d7d7f7c0df0d4de132a436e476e905c4d141cba",
                "dcc831feeca77f477f63106041e2c74f23ffc823372d7b2aa1dde2bcb6f41972",
                "824447ae811a9d8d7f8fc0475882cba57c194f4b2f27cb7c376c3d90bd78c1ff",
                "9d02b8962b5e555edb60f1dfc40cc447bbed28eb52de6bd5c30bb7321cae4bae",
                "bee2a0d172133a84270bda2d3e98be8661ab5807b5c99be2af72aceb74d315e8",
                "75e20ca7f35567805be665884bff09aa984670d12e11fd9894fdebf4d1941f07",
                "d8479ac754a6d6b36b15536a98cd0d2ee4488a3cf4e75bb00d9821b56137a865",
                "a3e75127e67943d28d8dde84f653aaa447689f25759003361854e8ec0ace0f2b",
                "279b608348e3102b11bdc9a5dcd0f3d74393ab1421edbaeb1129c6d8e5c6f227",
                "df6c1b5c48ca2c4c688d66661b68e1e3a52705861cd775c837f1a421ac713d4d",
                "859e9c733768fb334ae4b8e1de70d59e2d303606969b034b76fee42460cc61cd",
                "ad1fc56bc189cda84d85baff240722f25176e8dd51f10bd6687a051c940ba04c",
                "8d1400b037c8ce0269b4949faba87da820a5d865c44948cfd93e3a3880577b4c",
                "c6b465697a62fe53c523787a3489a87ad4a90a6dae8c88f7ced64ef18deefd58",
                "6d42b2b38c2f22041101d7c1043f5e49ad335828bdf507f485a5108534c37826",
                "a2d815a8af8e8df41219c967fc3109ca4ab3d3dfc7b67dd5176498d9560c2313",
                "dcbbb7ca86edf6d6d59c39a3939576b2f2a168479137ddb8916fa6891abbef68",
                "22cb1833e1ec512edb5a2440c03385ee690681caa39bea4514e28feac6cfcb11",
                "1c123b972ca7b7050cbc52d56787f0e1613fab76fcc4e50a8b2fe3cc434dcb5e",
                "5846850aab217977f040bb1b361a4221d0d5d550da70273e911e0b214f1c0969",
                "aa6539224df240ff96b0eae7884861bdd7b7c5261c5a9f840248fe1001295d2a",
                "a2a182fc3495c17e2c159ce1e20a7ed5046184152bb724cd734ff1307cb0a828",
                "9c4ae34f976eb35d3a7d8e58ce387c627c2b20e74ceea0f8b6162d9a488a08af",
                "d480c565eda9f31673cb75111e931954be9459f55824d2775d9840fce49e3925",
                "75e1414172c28fd05ebbbf6193d360b084ba9cf6c54d960e9b938f2f9eddbadd",
                "3ae174c81f8ac5cab774dd374e40926d78b1ab9968dc338fbb4a735ef9948749",
                "25f1de02e420248ac347b086eded60b0cbba6a6acca2b6fbfd6693052f440141",
                "9b3ea81f1670f9a7cbd97478b42de8bf37569edb6e2931568f2acb27e9a95511",
                "d40264970828edf9cfa54e4f405b24cd050f30a3b54481e355dc5f7cb1d1153d",
                "c3e9544e72697ab756791cea9a4cbe15bac7a64327a2d151294d5501101dd62b",
                "1cff680d7dd0e6f0dc7f16d4e1d0ceffcfb557034a19466a55dee4cba737404e",
                "ea56b2d072f809485b494a6583f83c5d810b2e45bd6ea1db49457547cae9a76a",
                "8541fc19d647e9ba58c85d6de2fe693a461ac98555cf892c9f33d59c48329eb1",
                "789fafe60740db2dc02b7f940bfbed102e99c931fef7fe625e1c159aae3ef541",
                "58085de9fcee22079ca7350716431f7ddbf190f7b551a89da0a5945dd3965af6",
                "53cc1002c42e8244ab5b7d7ffd77bc3eb298a19ac68448b134d4c7987acd510b",
                "d0209f9302f0b7ef0e54c5c4ba2045efd9c10d9a47e560f42a4c8e2c2c3c203a",
                "560f8c9ae27134ab4dee8a2d4a11c7f4b198e0c0e973c32b9bf580a97704e22b",
                "568f164b290fbefd0bbb77c97db12f40c865e1041f7a68265875178016da7e94",
                "7344abe4887f46125a75cf5ba859a50a61c9a671d9a6fc4e5420ea38cca15876",
                "cda7f9cde61ccff56245986b6bcd796058d1cd08b4cb75d9a0dc2a9dbe5788f2",
                "4141500df699cdcceb2ae93962bb81570bfbd3cc743224e9ec718d1447f4b418",
                "9fa4a0ab694e828bf15b49c7a02f664a433867755220d05135491ef9586c2c1c",
                "d0547a0b610a4d7b6696a8cd49fbfb9e4785f4012db92c2fd0f3f277694f0e9f",
                "af5d02bbcba1785997af8dd3276033fb37f5043116d63d351c0c123912c4b4c6",
                "43f9696454f48e6edc7229907c43af7121190010339d8f14b60054800b57cdd6",
                "f758d31e8f488823438e3644970fa1038383a2bd6e53700497ffb89727aa7c27",
                "06cf41e88fb4657f97ba81f91d42ebdc7f8f958b3c54cc8015919ded8f542838",
                "932be47f5728d0a6260493f852ad9d029c9ec7e647273396f499e3eb4f958aa5",
                "73f1fa205cb670f3bc21a200068e49da95653322718649c8418d7cb9e57478f3",
                "c6d3c788021c3fe328e1a2f91808edf4bc42a8bf9f2631c0467cde9f5239f02c",
                "2494e00253514eb46bfd3f3f600c380eb76b34ed485f92ac7d05bd8b6bf0fbb7",
                "cf914bdc8aef8b8e0c1d38a6d1cd62d9c73ed1bfbc5bd09d2c2e5fc44e11145a",
                "c83500b6f28f0777a7c5563920f79756b0994d23dfa333f75950648fd12a2362",
                "8236de476379285d88810dbb2989d3d7175b29ebbeab80a98eb193de5032bdf4",
                "35553f25dfe0ee941a8d51d53a551ae9ea71168ee3a85e77fa79ca59f1bee2cb",
                "68a9b9f4779d40e6ffa496799f1fa6bc37ea24d7204d5cd6455ceeb00fa9a383",
                "341c1b7168567ee17f856e59377df4184ec59caf26dd44fc9e86fc74986e0c7d",
                "f652d007955b0717ec0998f8c47c77e20e92b73762f576f0c33ef335fbc535bd",
                "d841267f9f87d8a0f84d4d84b5393c592909276af49eba14acef20345d914a54",
                "e64da2097dba4cb76110723951ce5a1b69507922dd8eed0a6018a82777a3f047",
                "1893882cf9db4bab8e434e9132b78b5fd7dd4d3d62a1aab3055e9a3ee5d1b5be",
                "fbd2abdaa550c1dbb0ca16326d575e56ef2730836a9454fa4ecbee0d932ab402",
                "a221f6a393fb5a17ae70e8d75f99871f8fdd1bb8ddf4b8ca770e6311ca8badf1",
                "cd37605d9b86b75db65f4363c3ee2a1ef0c4ecbfd34e498001fbc35fbd22a951",
                "0f36ef43483cc45c39aca67eee2546ffe5a3a89aaed3eeac3427bb250213b409",
                "dca6352b5c4e7c3645433c04f78f724fe5c333fc87488364e863eb82a40a4ba6",
                "d52a40b1546d3bc794bd5b75203e3127a47a8aff91525b4b83ad0c5442f2292c",
                "7f2d48ec8dc08ea02e380695faf1ba8f80be3117cefe69244891224ec368e589",
                "5d9b9846760a49afedfa209c131ad101ce5b340c1edec8566977d828151568b4",
                "7624937d8a4f646b11a21f57020c08d1e76bfb73042b83b2d579fe509fff59f9",
                "99aa2add8cbaf6de03a86282d7ba9d3493db9972cd93093b05c68b1a96faecea",
                "80c506e25499ae7d8324acb59b090fac61b58df5d41fac56d5ca342f00041326",
                "f4b91abcc348ccc2f187d12735f5e85f8664e981d0fb74cc5219f6afbbfd12be",
                "9a92e5149a9df65ee19016f89c99ecb883bcfb2d69aa13c603a33ffe9d5ed99c",
                "d76e1e470d33ffa97f64f2d9b94e30b374321e86f4158664ce561b04630ad217",
                "f22d37316c33bb9a5455ef89c00f26f9fc0cc7ec911697fa90bc77abd1b2b327",
                "13d0b773d4513f9918beb09f648e8a3b5018fee5eccb0db1fc484cb59c9a328d",
                "e476e25c7f8969b1c576488532c0708cfe2463437026d650c997d4157bb6483f",
                "6c91dab723bcc850890039d0bc528e6ce67118a4576274d0fd01517c1845a6bb",
                "b669aa6c370719189444c0aa33fde5e14f51c842b2a5145a818c5cdfa2c77444",
                "ad5228e1b8e781abb496fc9075c438f2071fa26ac1275bcddc6d7e748519edf5",
                "3188b9d1505d20b7abb27dc53cd99e13a8b7aa6874756b4555a9cf6d5f80bb14",
                "d6941c9e30f55eee236314161fce0cbd09c38b47c6c5c8a663218a072893dc0f",
                "6fa376b7354980b23fb95e415b3d36bc30f16fdc7e0e654bc2bf34b6ccee88dd",
                "079f7ac9c42bdb208c42c8770ceba4dc9c7f56da81406598b518b6e8c27e5d98",
                "4c4cc9e434ca77645102e87cbb33ddccd03187cdea740fe644741d049d6ae202",
                "abbcd57c43b7968d0beac550190892c575fb3785658dd398500a0b3153243dfc",
                "ef17738907f249a5420a30314f611702a5ccccbbafdac5aba876156bd4baecf7",
                "ebc5b3f2b50b3dc1b223f6bcdf270c5308a5c8367395f839a28ae4cdb19ee034",
                "d34c1374ec55364205beafeb086286f2ad45c8c709d7f0ae59c6dd7dba6480c4",
                "f0f98955aa8a2c31dfcc242b324d85977f7698fc05e65f1eee7a000cb502046e",
                "4341eba6e77351ff7de64396cd2bfda8301a93d14a59c6338e21be8394970bfc",
                "a13583a02c1d354ae82cca6048338afe4d81de183dfb9a40fca1d3b07834b1d5",
                "779d54b69be428f3ef3d59224f22d5f2104dbedca88005dc8020596ec6ffb310",
                "5d31d3989f7b3752139aea4b58d4bacee5613d7f10a069cbe376640f85d32296",
                "008383d0d32d0b3c734d25b8403095ab72e49b2efa5766f00f27edb7e91686b9",
                "55af89e642f41c33e7b74be6aecf9086a204a6babf02450507dfeaf92b962803",
                "618f1c931341fc8c831a6b4a12093d77c80afa169b3a627340d374d42ede3d19",
                "02af0b0a4e12ad03beea08751a3636720abf46d77caaedde1932145d437cfe3a",
                "fbd9aec07c0a2d83f97f139a0fda2820b7e8aab5cfe06f0bc0f12bc3d4fe88c9",
                "5517fffec631230663984a404841b5a1737213434cce709cc663d999bb668f41",
                "6662f10aa4237fd80c87736e3076644a069c9b162cb7246c6e81249cba5bff23",
                "5effd03c7eab92a77ca2adbd56469c9f782a80576b8997b3a3b6df2fc923788d",
                "8d0b6913627626303a9c975e218cd70039003a630c1850fb9e8dc96033d95b0a",
                "2e9c21d331b40c8d74aad5a73324416c1267124f3a4be5abb97a2853bc233b01",
                "cd20ed9192062c76d97fcb4c3f6a2b213fc10a49a2557c557fd7d593e016ac1e",
                "6d1098ea4407f8d71c08b973eb145dcde80b2bb8978462db6a58e310e59a1f53",
                "521202ae51d4e2463ca49881238a85bcad90f71e899d9719d1cef41e95786485",
                "faa8d50a92bf30a65678047a1a36f7f0992122809543c54a9c46e65b820be308",
                "0463faac2a6ed268a63629315428f1d58a23f1e629788fb593e5177dd4edb324",
                "e49353f9f62ec47901885d81d017440c0d1eadcc233ee947292553006530f460",
                "a7ea98ac890b5743b4fdee583df8377987946f8690d87304173258852fcb6cd3",
                "c448afef732fc4fb35938fa8b73d8937406f87f2a9d814046f6db46fd8e707da",
                "105b09f29537ef0448f6728f725e569686e748e7338c4a52036f581872b90d6c",
                "5358e823c6597484b8fec37ee1a9714ed39161f5fca90bfd014426b73c65e83c",
                "30960af8f9733413cb42f31fc26ed7409cc08c84b544ba66026d3215449d5e69",
                "e6a2cf09d1f4de348f2bf85e8ace1bc7450955283a976b62bef2b3fbdc300be6",
                "e5b2f13467cd4a8bee6dee72ab141e711e4e788b79c1e698f8e37a262237795b",
                "1b8f038d8887ff7527535f14f41df5a0a78abe548b7343085b103366ee1b7e21",
                "6ffd757e613442af5797b22ac4314f63db68a4b250bf26f94cf6bb23e62d9b9b",
                "7fb4c29c4795ff7bcea2d4edc1c0e35e648536e823b8cac5705b0de2587794a2",
                "a074039cd90c09014c589ae92f808b7a07a5aa57fe459acca59c44142b29d568",
                "89835be070c0cfc120dad25c78b6888383d28037b6384fc4fe0b10bf87821800",
                "7484c8e454f052105900933c674c352f6e7b67be1f52544e21831f3c8aa36deb",
                "92f2bfa5ab973d3bd94f37beec1ee0a303b8f2e33e697b9a0eb0c5b38a3c19ff",
                "79c886213c4af90460c5d0c2916dfcc8cc4f30722ae7a58106ed49d41395648f",
                "50a3ece87a6d4afdf096145eb5b024076bdd56e07d6af9f89d5e258ce1a0c80d",
                "212770e8d58ac06aa3724e88597cba80fe30eba83100de2cf5cf81f57e90397a",
                "df0595ded0537bcc2d93f18b037d123ffb2c07449fee986beb5c600c811ca9f1",
                "ce85d0b1922224e84f6238e975b94300f063e5978da7e3d6371f37b203887905",
                "2d3a05234381a97b7a20f9fed74c6225623609f18d4b383e5f7c0de61f78181a",
                "cf6cdbf16a8bd7d2f6950b9961827fdf22909ff704f4bdbcbed6037811277b1f",
                "4a58da8ab7bc065d1b3a50b1cbc7398f2f0584fe66c40795f413eb3f803317f6",
                "02a8d6cd652be5b7a7c9a4d5e6a7c872aadb7d7c4fb782afcabb625643e5773d",
                "8d2ad8fb028d4e6add596655854d6c33c8f66f17a48c3616db701d1a17352f69",
                "67e28cad06cc7b38ab9a1485686c64f21a10a9cc0f26efb18b35a869aab49ca7",
                "3aebf18a874c01a1e524f4182082ff596c016ddc8961e25843b75900191d878b",
                "08ab0ccb81824f77f0c80868f0b9fa16dce7de9f51775a845c877349999e158d",
                "cecd6d93c77807e6fb3cd3e9169126db0a8c56f873346ab4b148733d7dd1cd3b",
                "26c3131ea8582c120bb0fd65205081d141195ea5ab82187ea074592fc513ee10",
                "55dedd21e92ace6f67230d7ab34b3a3ae405129919ba3dec7e5da840cd10d7c3",
                "e4cf382096504b9a9d3d2f1238917deccdd41d634418e1af8911cf26b7e166e9",
                "4bbba9dc620fde96efa5c37f59d5ae42aa8371fff9fa015ed21485dc8a4660d8",
                "a402233a246707e8ad1781180bcbcf4cb49f799b871f7f5c8d0b84975882fc1b",
                "6f6d4ec73e66e7ddae3b295b2ff3f3f22871a13330ae6408f68b9d1edac5c767",
                "2a8bf6bd8b09f1f626a3f58fa658a3872488f01e314ce13be02fc4abcf20aaf3",
                "e599063477f1fdb8132c01501fdfd30f4cbce80272781db6ba0e2e28177c4cd6",
                "4959a210d1d7c90513b13d78ada6bc544d2b7fecd5ae16306897f0b28ba2bb17",
                "7ca519a0d6d49e1a8a672fb97a215bf0041d9a40cc0f0b7a4cd475984c105376",
                "5632cf0dfd8792c60b772e6dadda40db72ca17f79d3b7c8b0b3917df2b77a880",
                "48fe4a313dd5fe6f9f5f95d02f2e87d62891ee25d79e62edfecec0dd7154a745",
                "b2c29a82f108b28a7ab572f381f6bbec83633b3b97a967d2de7eb6e105e79bd5",
                "afe480de9dc874aafd5d8ed3501a316d9ad98a3bf68cfc6314ead878b8d9aeff",
                "8c6f5072d87f81cd32b058a4fc466c0280b7bc7116a0a437c3218eecfcc4d2df",
                "124dcf7379b9693497ac47fe9d9ffd59a32919d17c679887a0bf7a8f6b6ed211",
                "a97bddf9ab2a127aff53951b8d8fad36230c0596b9183b9faf88b3a06b1a0c9d",
                "d019ac2397d9560f41e9681830eb80b4fbe2d0399eb29d91e6bd1ebbd9de8791"
            ],
            "type": "XHR",
            "firstPartyCookies": {},
            "firstPartyCookiesSent": {},
            "exampleSites": [
                "korben.info",
                "www.sothebys.com",
                "www.wolfandbadger.com",
                "community.t-mobile.nl",
                "www.tourismvictoria.com",
                "ci.lubbock.tx.us",
                "openclassrooms.com",
                "www.mcleodhealth.org",
                "www.maisonette.com",
                "kavehome.com",
                "thesolesupplier.co.uk",
                "www.coursera.org",
                "www.rowohlt.de",
                "www.conduent.com",
                "www.travers.com",
                "www.revivalanimal.com",
                "www.nurumassage.com",
                "www.justspices.de",
                "scentsy.com",
                "www.ms.gov"
            ]
        },
        {
            "rule": "algolia\\.net\\/1\\/indexes\\/*\\/queries",
            "cookies": 0,
            "fingerprinting": 0,
            "subdomains": [
                "y2y10mz7jy-dsn",
                "2qwlvlxzb6-dsn",
                "i2uwp1cwqx-dsn",
                "eq79xlpiu7-dsn",
                "9nhgaoxpjg-dsn",
                "8etu77zv14-dsn",
                "6x6rkba85v-dsn",
                "t5qjjs38p2-dsn",
                "dirgdxwm7t-dsn",
                "7xxlgnqrtz-dsn",
                "uok6vs5ov2-dsn",
                "9ioacg5nhe-dsn",
                "g6qbk0086l-dsn",
                "drp4o45g5t-dsn",
                "h5yovykinu-dsn",
                "cu5a135pq9-dsn",
                "dkvugqjm5c-dsn",
                "6z1x4vph2b-dsn",
                "xxh6l2io6p-dsn",
                "xn5vepvd4i-dsn",
                "43kmjyqoga-dsn",
                "bc4sa39fg5-dsn",
                "1gth8h5lzo-dsn",
                "mnrwefss2q-dsn",
                "b5iu9lvsk0-dsn",
                "qvwwc7jv7a-dsn",
                "vfm4x0n23a-dsn",
                "msn7pvpzhu-dsn",
                "vtvkm5urpx-dsn",
                "c738agbp0j-dsn",
                "kgun8faipf-dsn",
                "p28kr2j94g-dsn",
                "ulrh5gm865-dsn",
                "fd1a5vmjfk-dsn",
                "ujjak2x1py-dsn",
                "7msii23cds-dsn",
                "f49rvkeckz-dsn",
                "nhehr8xbao-dsn",
                "ampaw8yccp-dsn",
                "eyaffs0rc4-dsn",
                "lkay4pjwx5-dsn",
                "fa677j9qji-dsn",
                "xil6vmff24-dsn",
                "2125ht9m59-dsn",
                "ysu8j82bmw-dsn",
                "ookh1nfe65-dsn",
                "1hwjvf93zd-dsn",
                "3x73s963e7-dsn",
                "qjaugn1pvu-dsn"
            ],
            "apis": {},
            "sites": 56,
            "prevalence": 0.000382,
            "cnames": [],
            "responseHashes": [],
            "type": "Preflight",
            "firstPartyCookies": {},
            "firstPartyCookiesSent": {},
            "exampleSites": [
                "www.puppet.com",
                "www.iheartjane.com",
                "www.clearly.ca",
                "www.grailed.com",
                "www.bureauengros.com",
                "www.adameteve.fr",
                "www.decathlon.ca",
                "www.thegamecrafter.com",
                "www.greenbook.net",
                "projecthub.arduino.cc",
                "arduino.cc",
                "www.hessnatur.com",
                "www.travers.com",
                "www.the-saleroom.com",
                "support.arduino.cc",
                "docs.arduino.cc",
                "www.whisky.fr",
                "www.relaischateaux.com",
                "www.northropandjohnson.com",
                "www.manomano.co.uk"
            ]
        },
        {
            "rule": "algolia\\.net\\/1\\/indexes",
            "cookies": 0,
            "fingerprinting": 0,
            "subdomains": [
                "ic23zxnzkt-dsn",
                "42pgxxd20k-dsn"
            ],
            "apis": {},
            "sites": 17,
            "prevalence": 0.000116,
            "cnames": [],
            "responseHashes": [
                "ad91b13c1b60a6f9d1239083fb580c64c24446351a920358afe42f844b77b31e",
                "f5d6dec8161c1041a23f253c730e5510ffda63838e18e54e353675ec24433ab2",
                "73a8f2f4729b7aede24017c5addb348c3dc2903a42eccbd74840b2057e018e1e",
                "b791025359b4735602a66188abdeb713da12180209f0c3442cb61f3c2e618c4e",
                "ebd48c9167c4f713d46d2f2e4b5fbe6f74197225251049d904bfd1ffaaa18d9d",
                "b92d605277aa183badfb3a8f4574c8cecfb166f9643e2b0d3bb5dc0c8623b1d0",
                "36cf72dd018541e2930a2c7b1bb489d7693f009dc6b8ed5a274e9c9d10495f95",
                "f26e1fac7da104a4fecde245c5ab54b68b82a07cc54b8399df7a196fd6e89481",
                "32e9b1f554eead9f638be0897b3a3be6d2aceb8695fa28fad4d638efea682fe5",
                "121f765b8c68215a71a9edbaad5cb9872622203e1953d14a65f6b372173bcba8",
                "1a48a9689c835872a891c4751e29ef30581e73a43943d3cf9badb49d8de85106",
                "5bc165ef45699d87a245f7575651c1ec232a774ddeda14d9b3bfe7d6900a690f",
                "25b64494eb5b055eac0be5544893ce18d351c81afbe6eb96b5b23a7376634817",
                "840a561d4e1f9ce644ed39f2c40e53421e57e435802c3708df6241719530ec7e",
                "ed50a8547582a894f14c6d7e16d9499da6dab006f2b1142863868da38d93ff54",
                "4b7012458b3432c84fd275e4d4274e968331c622aa559af60be64d624893c79f"
            ],
            "type": "XHR",
            "firstPartyCookies": {},
            "firstPartyCookiesSent": {},
            "exampleSites": [
                "acumatica.com",
                "community.acumatica.com",
                "community.dyson.com",
                "community.miro.com",
                "community.ns.nl",
                "community.qualtrics.com",
                "community.t-mobile.nl",
                "community.veeam.com",
                "community.zapier.com",
                "community.webroot.com",
                "en.community.sonos.com",
                "forum.kindertelefoon.nl",
                "forum.kpn.com",
                "hilfe.o2online.de",
                "insider.razer.com",
                "next.nutanix.com",
                "www.berea.edu"
            ]
        },
        {
            "rule": "algolia\\.net\\/1\\/indexes\\/menu-products-production\\/query",
            "cookies": 0,
            "fingerprinting": 0,
            "subdomains": [
                "vfm4x0n23a-dsn"
            ],
            "apis": {},
            "sites": 3,
            "prevalence": 0.0000204,
            "cnames": [],
            "responseHashes": [],
            "type": "Preflight",
            "firstPartyCookies": {},
            "firstPartyCookiesSent": {},
            "exampleSites": [
                "getfluent.com",
                "www.iheartjane.com",
                "www.surterra.com"
            ]
        },
        {
            "rule": "algolia\\.net\\/1\\/indexes\\/menu-products-production\\/query",
            "cookies": 0,
            "fingerprinting": 0,
            "subdomains": [
                "vfm4x0n23a-dsn"
            ],
            "apis": {},
            "sites": 3,
            "prevalence": 0.0000204,
            "cnames": [],
            "responseHashes": [
                "53506b8945b2bf281268d47e2392082edc411ef1d04fbab557c3409890c1949c",
                "46750eeebb49e7b167d9feb5780a0607ae3cd014068cbf36ab88e70ea213be81"
            ],
            "type": "XHR",
            "firstPartyCookies": {},
            "firstPartyCookiesSent": {},
            "exampleSites": [
                "getfluent.com",
                "www.iheartjane.com",
                "www.surterra.com"
            ]
        },
        {
            "rule": "algolia\\.net\\/1\\/indexes\\/*\\/recommendations",
            "cookies": 0,
            "fingerprinting": 0,
            "subdomains": [
                "3q37gxuu9i-dsn",
                "drnz5p2ski-dsn",
                "04ie0383at-dsn",
                "3g3t2s1ucd-dsn",
                "zxbjr4u3np-dsn",
                "5vuajpxyrn-dsn",
                "pxa5v6axkq-dsn",
                "zfdm04fn4z-dsn",
                "cfaxieb3i5-dsn",
                "nzylatfz2q-dsn",
                "ok42bx2aqd-dsn",
                "6m60w1zkr5-dsn",
                "ssdqwuevb6-dsn",
                "mb13iy345y-dsn",
                "hzoxaduqy8-dsn",
                "zbpf4p5c1e-dsn",
                "ubqp4aes36-dsn"
            ],
            "apis": {},
            "sites": 18,
            "prevalence": 0.000123,
            "cnames": [],
            "responseHashes": [
                "5f7b98853c25b7d4daefe47d3d5a124e78489187d82314d056f3a52e715ae9bc",
                "354522b203591cb83cf4c5f5d73a0be743c6fd327bdbca3ebcf0a7e8c761668d",
                "2ee78c724e5a41707b48e909858e15cd0a2e6577a69cd4e4fe69dc84208b57fe",
                "356c86fc208461818b7ef90e6f5259ca2b508fcc6b94dee52ce4d7263e872763",
                "390c9aadd500c8721c9f69b0a12aacb8b2418f933a6619a1e7321b991e3d6880",
                "d03e266d1f9e9b701bd2d73806d9d7ae72ea487a2bc0034232e779437ba8a1f2",
                "44f9f3064a9fa5ddcf4605eb7c5f9bae8a8a205ff1b3e9e94a87afaeb3862916",
                "788b1fe841577fd35da9644e1b855ec6408c0770cef18a858bd6ac32a4ff30af",
                "117bc9fd61d74a293d12cca4fb233030e03ff45f0cad19c1f9b010055445ed11",
                "b57f503611bd449a3371a85f11d902a22f6b608537d110575b7a516342e9dcd3",
                "ba10d0059d359682970e0c31f57dc26a331a0d09a5b01c2da901231a42d12f07",
                "52eb3d2a000adaa647f6b54bdd257bac01df07de2349fbe2a0ffe1f4c72248f1",
                "dddc8dd8228c0b18293404dd1bcc7c57630552a5a0a42057b916c00709f5c1c7",
                "85478eaa54afff2a2e8996bf27c6e3a90917979bdb521ca1b3c06be0cc0b2cff",
                "068056ccf08f9d298432b61ecc28b62984ce0741a7d3b0d78a3602a4bf68da85",
                "89db030463ca80b55a0984d7a5efde34757012fe40950dc77a58eb2098aadb1b"
            ],
            "type": "XHR",
            "firstPartyCookies": {},
            "firstPartyCookiesSent": {},
            "exampleSites": [
                "hasbropulse.com",
                "mejuri.com",
                "shop.sportsbasement.com",
                "ucam.xxx",
                "www.bulkreefsupply.com",
                "www.burpee.com",
                "www.filson.com",
                "www.foraged.com",
                "www.fortnumandmason.com",
                "www.ilgiardinodeilibri.it",
                "www.infinitymotorcycles.com",
                "www.jpplus.com",
                "www.lifeway.com",
                "www.vapesuperstore.co.uk",
                "www.wineenthusiast.com",
                "www.winemag.com",
                "www.wusthof.com",
                "www.zeeman.com"
            ]
        },
        {
            "rule": "algolia\\.net\\/1\\/indexes\\/external_article\\/query",
            "cookies": 0,
            "fingerprinting": 0,
            "subdomains": [
                "i4melyi9o9-dsn"
            ],
            "apis": {},
            "sites": 2,
            "prevalence": 0.0000136,
            "cnames": [],
            "responseHashes": [
                "66389a058004190e15a69327f7a0a12db4fedfde4b84fbcf48b5c776702534f3"
            ],
            "type": "XHR",
            "firstPartyCookies": {},
            "firstPartyCookiesSent": {},
            "exampleSites": [
                "vrbo.com",
                "help.vrbo.com"
            ]
        },
        {
            "rule": "algolia\\.net\\/1\\/indexes\\/prod_cruises_en\\/query",
            "cookies": 0,
            "fingerprinting": 0,
            "subdomains": [
                "ogg7av1jsp-dsn"
            ],
            "apis": {},
            "sites": 2,
            "prevalence": 0.0000136,
            "cnames": [],
            "responseHashes": [
                "8481caaa225c2c5dbdc578cbc285596ef236a81f6d5a564fef2b89217323e563"
            ],
            "type": "XHR",
            "firstPartyCookies": {},
            "firstPartyCookiesSent": {},
            "exampleSites": [
                "silversea.com",
                "www.silversea.com"
            ]
        },
        {
            "rule": "algolia\\.net\\/1\\/indexes\\/shopify_products\\/query",
            "cookies": 0,
            "fingerprinting": 0,
            "subdomains": [
                "93vtyj8vuk-dsn",
                "668rb43gd4-dsn",
                "h5yovykinu-dsn",
                "mb13iy345y-dsn"
            ],
            "apis": {},
            "sites": 5,
            "prevalence": 0.0000341,
            "cnames": [],
            "responseHashes": [
                "e458eb74f4072eca27d009fe7b4539ccdc3f38a32d97632c4ee5a406e353be6c",
                "ec9503f4e962b7747a9fcd41cb88626f72adb76d87dc62d333622d3b70e0f5cc",
                "c0da0bb7269b1d614b61217ae71331df08beb13095add9ccce43b740ce3651a3",
                "61afb27063e27c270c2554974fddc71a737f105287a0cae84e244a7ce09d685c"
            ],
            "type": "XHR",
            "firstPartyCookies": {},
            "firstPartyCookiesSent": {},
            "exampleSites": [
                "thefeed.com",
                "wildforkfoods.com",
                "www.bureauengros.com",
                "www.staples.ca",
                "www.vapesuperstore.co.uk"
            ]
        },
        {
            "rule": "algolia\\.net\\/1\\/indexes\\/production_edudirect_programs_ranking\\/query",
            "cookies": 0,
            "fingerprinting": 0,
            "subdomains": [
                "yg3l958nut-dsn"
            ],
            "apis": {},
            "sites": 3,
            "prevalence": 0.0000204,
            "cnames": [],
            "responseHashes": [
                "537ff5d3a12440694dc369097845f9c612ad52bb25f3d2efe72b89fc06207a6b",
                "4b02ae4da6ec853662d712f0024141959067556424dd5a527e95fdace052ca2e"
            ],
            "type": "XHR",
            "firstPartyCookies": {},
            "firstPartyCookiesSent": {},
            "exampleSites": [
                "accounting.com",
                "www.accounting.com",
                "www.accreditedschoolsonline.org"
            ]
        },
        {
            "rule": "algolia\\.net\\/1\\/indexes\\/production_edudirect_programs_ranking\\/query",
            "cookies": 0,
            "fingerprinting": 0,
            "subdomains": [
                "yg3l958nut-dsn"
            ],
            "apis": {},
            "sites": 2,
            "prevalence": 0.0000136,
            "cnames": [],
            "responseHashes": [],
            "type": "Preflight",
            "firstPartyCookies": {},
            "firstPartyCookiesSent": {},
            "exampleSites": [
                "accounting.com",
                "www.accreditedschoolsonline.org"
            ]
        },
        {
            "rule": "algolia\\.net\\/1\\/indexes\\/everest_search_avg_rating_desc_production\\/query",
            "cookies": 0,
            "fingerprinting": 0,
            "subdomains": [
                "y1fnzxui30-dsn"
            ],
            "apis": {},
            "sites": 2,
            "prevalence": 0.0000136,
            "cnames": [],
            "responseHashes": [
                "020b2bd1943d56de65afe05b04afe2e11f7f0d96bb8a0094116897b340120482"
            ],
            "type": "XHR",
            "firstPartyCookies": {},
            "firstPartyCookiesSent": {},
            "exampleSites": [
                "americastestkitchen.com",
                "www.americastestkitchen.com"
            ]
        },
        {
            "rule": "algolia\\.net\\/1\\/indexes\\/*\\/objects",
            "cookies": 0,
            "fingerprinting": 0,
            "subdomains": [
                "j8n8i8ke2y-dsn",
                "mnrwefss2q-dsn",
                "day79mubw3-dsn",
                "flwdn2189e-dsn"
            ],
            "apis": {},
            "sites": 5,
            "prevalence": 0.0000341,
            "cnames": [],
            "responseHashes": [
                "c72eaef9f39e6882a343397cd74463301d9f960a8f68ca4db1526a908a7c39d8",
                "5021e624e752b001ce3e3846e8f158ed4aeb93a4c9a72fdb35a0c5b14a0eea84"
            ],
            "type": "XHR",
            "firstPartyCookies": {},
            "firstPartyCookiesSent": {},
            "exampleSites": [
                "azurestandard.com",
                "www.azurestandard.com",
                "www.grailed.com",
                "www.planity.com",
                "www.rema1000.dk"
            ]
        },
        {
            "rule": "algolia\\.net\\/1\\/indexes\\/Baratza_BUS_ZCG\\/query",
            "cookies": 0,
            "fingerprinting": 0,
            "subdomains": [
                "vbt275cjrz-dsn"
            ],
            "apis": {},
            "sites": 2,
            "prevalence": 0.0000136,
            "cnames": [],
            "responseHashes": [
                "c0eedc7541d3ee7038d4003b44999943eacccb3b96bc58065590b3b9c4f09bcd"
            ],
            "type": "XHR",
            "firstPartyCookies": {},
            "firstPartyCookiesSent": {},
            "exampleSites": [
                "baratza.com",
                "www.baratza.com"
            ]
        },
        {
            "rule": "algolia\\.net\\/1\\/indexes\\/Baratza_BUS_ZCG\\/query",
            "cookies": 0,
            "fingerprinting": 0,
            "subdomains": [
                "vbt275cjrz-dsn"
            ],
            "apis": {},
            "sites": 2,
            "prevalence": 0.0000136,
            "cnames": [],
            "responseHashes": [],
            "type": "Preflight",
            "firstPartyCookies": {},
            "firstPartyCookiesSent": {},
            "exampleSites": [
                "baratza.com",
                "www.baratza.com"
            ]
        },
        {
            "rule": "algolia\\.net\\/1\\/indexes\\/shopify_products\\/query",
            "cookies": 0,
            "fingerprinting": 0,
            "subdomains": [
                "h5yovykinu-dsn"
            ],
            "apis": {},
            "sites": 2,
            "prevalence": 0.0000136,
            "cnames": [],
            "responseHashes": [],
            "type": "Preflight",
            "firstPartyCookies": {},
            "firstPartyCookiesSent": {},
            "exampleSites": [
                "bureauengros.com",
                "www.staples.ca"
            ]
        },
        {
            "rule": "algolia\\.net\\/1\\/indexes\\/shopify_products_fr_qs_analytics\\/query",
            "cookies": 0,
            "fingerprinting": 0,
            "subdomains": [
                "h5yovykinu-dsn"
            ],
            "apis": {},
            "sites": 2,
            "prevalence": 0.0000136,
            "cnames": [],
            "responseHashes": [],
            "type": "Preflight",
            "firstPartyCookies": {},
            "firstPartyCookiesSent": {},
            "exampleSites": [
                "bureauengros.com",
                "www.bureauengros.com"
            ]
        },
        {
            "rule": "algolia\\.net\\/1\\/indexes\\/shopify_products_fr_qs_analytics\\/query",
            "cookies": 0,
            "fingerprinting": 0,
            "subdomains": [
                "h5yovykinu-dsn"
            ],
            "apis": {},
            "sites": 2,
            "prevalence": 0.0000136,
            "cnames": [],
            "responseHashes": [
                "6fd995fc40e56ae2e77a9282bbf928ca2146cfc4d8483cfda063056f2da43c8a"
            ],
            "type": "XHR",
            "firstPartyCookies": {},
            "firstPartyCookiesSent": {},
            "exampleSites": [
                "bureauengros.com",
                "www.bureauengros.com"
            ]
        },
        {
            "rule": "algolia\\.net\\/1\\/indexes\\/shopify_products_title_asc\\/query",
            "cookies": 0,
            "fingerprinting": 0,
            "subdomains": [
                "h5yovykinu-dsn"
            ],
            "apis": {},
            "sites": 2,
            "prevalence": 0.0000136,
            "cnames": [],
            "responseHashes": [
                "2133733b600d673455487f35e0e4614d2886301843a1437ddff2fa5effce595e"
            ],
            "type": "XHR",
            "firstPartyCookies": {},
            "firstPartyCookiesSent": {},
            "exampleSites": [
                "bureauengros.com",
                "www.staples.ca"
            ]
        },
        {
            "rule": "algolia\\.net\\/1\\/indexes\\/harpercollins-epicreads_products\\/query",
            "cookies": 0,
            "fingerprinting": 0,
            "subdomains": [
                "0iz6gtnjfs-dsn"
            ],
            "apis": {},
            "sites": 2,
            "prevalence": 0.0000136,
            "cnames": [],
            "responseHashes": [
                "78ab450ddd4dbd4f3d596780f625a4677c77dc55530ba9808ffe9e5b69a4088f"
            ],
            "type": "XHR",
            "firstPartyCookies": {},
            "firstPartyCookiesSent": {},
            "exampleSites": [
                "epicreads.com",
                "www.epicreads.com"
            ]
        },
        {
            "rule": "algolia\\.net\\/1\\/indexes\\/stores_prod\\/facets\\/brands\\/query",
            "cookies": 0,
            "fingerprinting": 0,
            "subdomains": [
                "bc4sa39fg5-dsn"
            ],
            "apis": {},
            "sites": 2,
            "prevalence": 0.0000136,
            "cnames": [],
            "responseHashes": [],
            "type": "Preflight",
            "firstPartyCookies": {},
            "firstPartyCookiesSent": {},
            "exampleSites": [
                "furniture.com",
                "www.furniture.com"
            ]
        },
        {
            "rule": "algolia\\.net\\/1\\/indexes\\/stores_prod\\/facets\\/brands\\/query",
            "cookies": 0,
            "fingerprinting": 0,
            "subdomains": [
                "bc4sa39fg5-dsn"
            ],
            "apis": {},
            "sites": 2,
            "prevalence": 0.0000136,
            "cnames": [],
            "responseHashes": [
                "38167a36ccb27c1d50480a4c7c19aafd6bc12f540ae9010d285f31af13860a58"
            ],
            "type": "XHR",
            "firstPartyCookies": {},
            "firstPartyCookiesSent": {},
            "exampleSites": [
                "furniture.com",
                "www.furniture.com"
            ]
        },
        {
            "rule": "algolia\\.net\\/1\\/indexes\\/Designer_production\\/query",
            "cookies": 0,
            "fingerprinting": 0,
            "subdomains": [
                "mnrwefss2q-dsn"
            ],
            "apis": {},
            "sites": 2,
            "prevalence": 0.0000136,
            "cnames": [],
            "responseHashes": [
                "1285bb6949b72e5a42fabb1e2101ac93916c7df169c8f53eb921ddce738d749e"
            ],
            "type": "XHR",
            "firstPartyCookies": {},
            "firstPartyCookiesSent": {},
            "exampleSites": [
                "grailed.com",
                "www.grailed.com"
            ]
        },
        {
            "rule": "algolia\\.net\\/1\\/indexes\\/Designer_production\\/query",
            "cookies": 0,
            "fingerprinting": 0,
            "subdomains": [
                "mnrwefss2q-dsn"
            ],
            "apis": {},
            "sites": 2,
            "prevalence": 0.0000136,
            "cnames": [],
            "responseHashes": [],
            "type": "Preflight",
            "firstPartyCookies": {},
            "firstPartyCookiesSent": {},
            "exampleSites": [
                "grailed.com",
                "www.grailed.com"
            ]
        },
        {
            "rule": "algolia\\.net\\/1\\/indexes\\/*\\/queries",
            "cookies": 0,
            "fingerprinting": 0,
            "subdomains": [
                "kgun8faipf-dsn"
            ],
            "apis": {},
            "sites": 2,
            "prevalence": 0.0000136,
            "cnames": [],
            "responseHashes": [
                "25536f52bdacaa7bbebec05db394276f198ebbab9734a5da2ae1dafea4f3c0c5"
            ],
            "type": "Fetch",
            "firstPartyCookies": {},
            "firstPartyCookiesSent": {},
            "exampleSites": [
                "linode.com",
                "www.linode.com"
            ]
        },
        {
            "rule": "algolia\\.net\\/1\\/indexes\\/prod_plp_en-gb\\/query",
            "cookies": 0,
            "fingerprinting": 0,
            "subdomains": [
                "j5nefinov3-dsn"
            ],
            "apis": {},
            "sites": 2,
            "prevalence": 0.0000136,
            "cnames": [],
            "responseHashes": [],
            "type": "Preflight",
            "firstPartyCookies": {},
            "firstPartyCookiesSent": {},
            "exampleSites": [
                "raleigh.co.uk",
                "www.raleigh.co.uk"
            ]
        },
        {
            "rule": "algolia\\.net\\/1\\/indexes\\/prod_plp_en-gb\\/query",
            "cookies": 0,
            "fingerprinting": 0,
            "subdomains": [
                "j5nefinov3-dsn"
            ],
            "apis": {},
            "sites": 2,
            "prevalence": 0.0000136,
            "cnames": [],
            "responseHashes": [
                "b26db66ecbbcdde09d75512e55c71d4bb64e9aaa1b111cac80eddc9096bb6d92"
            ],
            "type": "XHR",
            "firstPartyCookies": {},
            "firstPartyCookiesSent": {},
            "exampleSites": [
                "raleigh.co.uk",
                "www.raleigh.co.uk"
            ]
        },
        {
            "rule": "algolia\\.net\\/1\\/indexes\\/slido-en\\/query",
            "cookies": 0,
            "fingerprinting": 0,
            "subdomains": [
                "ic23zxnzkt-dsn"
            ],
            "apis": {},
            "sites": 2,
            "prevalence": 0.0000136,
            "cnames": [],
            "responseHashes": [
                "8ee41ff7da7c2cf9aa04ef150b5c037fcbefeb8c7789ab5d7759ddcb1d10f7f1"
            ],
            "type": "XHR",
            "firstPartyCookies": {},
            "firstPartyCookiesSent": {},
            "exampleSites": [
                "slido.com",
                "www.slido.com"
            ]
        },
        {
            "rule": "algolia\\.net\\/1\\/indexes\\/shopify_products_en_qs\\/query",
            "cookies": 0,
            "fingerprinting": 0,
            "subdomains": [
                "h5yovykinu-dsn"
            ],
            "apis": {},
            "sites": 2,
            "prevalence": 0.0000136,
            "cnames": [],
            "responseHashes": [],
            "type": "Preflight",
            "firstPartyCookies": {},
            "firstPartyCookiesSent": {},
            "exampleSites": [
                "staples.ca",
                "www.staples.ca"
            ]
        },
        {
            "rule": "algolia\\.net\\/1\\/indexes\\/shopify_products_en_qs\\/query",
            "cookies": 0,
            "fingerprinting": 0,
            "subdomains": [
                "h5yovykinu-dsn"
            ],
            "apis": {},
            "sites": 2,
            "prevalence": 0.0000136,
            "cnames": [],
            "responseHashes": [
                "00f10cb806057bcdeee8bf4feac96ccd303ce358b86af562989d87c1ab8631f8"
            ],
            "type": "XHR",
            "firstPartyCookies": {},
            "firstPartyCookiesSent": {},
            "exampleSites": [
                "staples.ca",
                "www.staples.ca"
            ]
        },
        {
            "rule": "algolia\\.net\\/1\\/indexes\\/shopify_products_en_qs_analytics\\/query",
            "cookies": 0,
            "fingerprinting": 0,
            "subdomains": [
                "h5yovykinu-dsn"
            ],
            "apis": {},
            "sites": 2,
            "prevalence": 0.0000136,
            "cnames": [],
            "responseHashes": [],
            "type": "Preflight",
            "firstPartyCookies": {},
            "firstPartyCookiesSent": {},
            "exampleSites": [
                "staples.ca",
                "www.staples.ca"
            ]
        },
        {
            "rule": "algolia\\.net\\/1\\/indexes\\/shopify_products_en_qs_analytics\\/query",
            "cookies": 0,
            "fingerprinting": 0,
            "subdomains": [
                "h5yovykinu-dsn"
            ],
            "apis": {},
            "sites": 2,
            "prevalence": 0.0000136,
            "cnames": [],
            "responseHashes": [],
            "type": "XHR",
            "firstPartyCookies": {},
            "firstPartyCookiesSent": {},
            "exampleSites": [
                "staples.ca",
                "www.staples.ca"
            ]
        },
        {
            "rule": "algolia\\.net\\/1\\/indexes\\/steelcasecom_production_na_en\\/query",
            "cookies": 0,
            "fingerprinting": 0,
            "subdomains": [
                "bcxurw325t-dsn"
            ],
            "apis": {},
            "sites": 2,
            "prevalence": 0.0000136,
            "cnames": [],
            "responseHashes": [],
            "type": "Preflight",
            "firstPartyCookies": {},
            "firstPartyCookiesSent": {},
            "exampleSites": [
                "steelcase.com",
                "www.steelcase.com"
            ]
        },
        {
            "rule": "algolia\\.net\\/1\\/indexes\\/steelcasecom_production_na_en\\/query",
            "cookies": 0,
            "fingerprinting": 0,
            "subdomains": [
                "bcxurw325t-dsn"
            ],
            "apis": {},
            "sites": 2,
            "prevalence": 0.0000136,
            "cnames": [],
            "responseHashes": [
                "584d125c8f647093770d28a648412415ff1ded90edd21627b30131d315eafc04"
            ],
            "type": "XHR",
            "firstPartyCookies": {},
            "firstPartyCookiesSent": {},
            "exampleSites": [
                "steelcase.com",
                "www.steelcase.com"
            ]
        },
        {
            "rule": "algolia\\.net\\/1\\/indexes\\/may_production_default_categories\\/5063",
            "cookies": 0,
            "fingerprinting": 0,
            "subdomains": [
                "1hwjvf93zd-dsn"
            ],
            "apis": {},
            "sites": 2,
            "prevalence": 0.0000136,
            "cnames": [],
            "responseHashes": [
                "3fcb298fcddec821d9890c5551849aa47c866d556e26beea5b7cdf8239ef378a"
            ],
            "type": "XHR",
            "firstPartyCookies": {},
            "firstPartyCookiesSent": {},
            "exampleSites": [
                "travers.com",
                "www.travers.com"
            ]
        },
        {
            "rule": "algolia\\.net\\/1\\/indexes\\/tudorwatch_search_watches_zg\\/query",
            "cookies": 0,
            "fingerprinting": 0,
            "subdomains": [
                "u5s8kv3uw0-dsn"
            ],
            "apis": {},
            "sites": 2,
            "prevalence": 0.0000136,
            "cnames": [],
            "responseHashes": [],
            "type": "Preflight",
            "firstPartyCookies": {},
            "firstPartyCookiesSent": {},
            "exampleSites": [
                "tudorwatch.com",
                "www.tudorwatch.com"
            ]
        },
        {
            "rule": "algolia\\.net\\/1\\/indexes\\/tudorwatch_search_watches_zg\\/query",
            "cookies": 0,
            "fingerprinting": 0,
            "subdomains": [
                "u5s8kv3uw0-dsn"
            ],
            "apis": {},
            "sites": 2,
            "prevalence": 0.0000136,
            "cnames": [],
            "responseHashes": [
                "eedcc55631c10886ef598ae4accc7b91a0a632e63518740a2a2029781de3d88b"
            ],
            "type": "XHR",
            "firstPartyCookies": {},
            "firstPartyCookiesSent": {},
            "exampleSites": [
                "tudorwatch.com",
                "www.tudorwatch.com"
            ]
        },
        {
            "rule": "algolia\\.net\\/1\\/indexes\\/help_fr-fr_default\\/query",
            "cookies": 0,
            "fingerprinting": 0,
            "subdomains": [
                "avcvysejs1-dsn"
            ],
            "apis": {},
            "sites": 2,
            "prevalence": 0.0000136,
            "cnames": [],
            "responseHashes": [
                "e491316c80864c538444d21b0a7debaa94e32bb09c25c6d653b24b0e30924a1b"
            ],
            "type": "XHR",
            "firstPartyCookies": {},
            "firstPartyCookiesSent": {},
            "exampleSites": [
                "ubisoft.com",
                "www.ubisoft.com"
            ]
        }
    ],
    "categories": [],
    "performance": {},
    "cookies": 0,
    "topInitiators": [
        {
            "domain": "first party",
            "prevalence": 0.6548223350253807
        },
        {
            "domain": "gammacdn.com",
            "prevalence": 0.0532994923857868
        },
        {
            "domain": "jsdelivr.net",
            "prevalence": 0.04949238578680203
        },
        {
            "domain": "donately.com",
            "prevalence": 0.04060913705583756
        },
        {
            "domain": "d3odp2r1osuwn0.cloudfront.net",
            "prevalence": 0.03553299492385787
        },
        {
            "domain": "iheartjane.com",
            "prevalence": 0.031725888324873094
        },
        {
            "domain": "dowpznhhyvkm4.cloudfront.net",
            "prevalence": 0.024111675126903553
        },
        {
            "domain": "sentry-cdn.com",
            "prevalence": 0.01903553299492386
        },
        {
            "domain": "datadoghq-browser-agent.com",
            "prevalence": 0.011421319796954314
        },
        {
            "domain": "realtruck.com",
            "prevalence": 0.007614213197969543
        }
    ],
    "types": {
        "XHR": 346,
        "Preflight": 81,
        "Fetch": 2
    },
    "nameservers": [
        "dns4.p03.nsone.net",
        "dns3.p03.nsone.net",
        "dns1.p03.nsone.net",
        "dns2.p03.nsone.net"
    ]
}