{
    "domain": "alwayson.ai",
    "owner": {},
    "source": [
        "DuckDuckGo-US"
    ],
    "prevalence": 0.0000136,
    "sites": 2,
    "subdomains": [
        "app"
    ],
    "cnames": [],
    "fingerprinting": 2,
    "resources": [
        {
            "rule": "alwayson\\.ai\\/embed\\/chatbot\\.js",
            "cookies": 0,
            "fingerprinting": 2,
            "subdomains": [
                "app"
            ],
            "apis": {
                "Navigator.prototype.product": 1,
                "window.innerWidth": 1,
                "window.innerHeight": 1
            },
            "sites": 2,
            "prevalence": 0.0000136,
            "cnames": [],
            "responseHashes": [
                "8fc8fa2d56271c0ab3e5eaa1bd5c2bc610c1ada5747833b738bcb4a7c797d3f7"
            ],
            "type": "Script",
            "firstPartyCookies": {},
            "firstPartyCookiesSent": {},
            "exampleSites": [
                "bvsd.org",
                "www.lewispalmer.org"
            ]
        }
    ],
    "categories": [],
    "performance": {},
    "cookies": 0,
    "topInitiators": [
        {
            "domain": "first party",
            "prevalence": 1
        }
    ],
    "types": {
        "Script": 2
    },
    "nameservers": [
        "ns-1103.awsdns-09.org",
        "ns-680.awsdns-21.net",
        "ns-1979.awsdns-55.co.uk",
        "ns-241.awsdns-30.com"
    ]
}