{
    "domain": "fuarden.pro",
    "owner": {},
    "source": [
        "DuckDuckGo-US"
    ],
    "prevalence": 0.0000204,
    "sites": 3,
    "subdomains": [],
    "cnames": [],
    "fingerprinting": 1,
    "resources": [
        {
            "rule": "fuarden\\.pro\\/engage\\.js",
            "cookies": 0.0000204,
            "fingerprinting": 1,
            "subdomains": [],
            "apis": {
                "Document.cookie getter": 3,
                "Document.cookie setter": 3
            },
            "sites": 3,
            "prevalence": 0.0000204,
            "cnames": [],
            "responseHashes": [
                "75f6ee175569665501e0707b50c0b24b429715f7b319c10d4b57432916507770"
            ],
            "type": "Script",
            "firstPartyCookies": {
                "user_id_t": {
                    "ttl": 2592025,
                    "length": 36,
                    "prevalence": 0.000020449897750511246,
                    "uniqueness": 0.6666666666666666
                }
            },
            "firstPartyCookiesSent": {},
            "exampleSites": [
                "banggood.com",
                "usa.banggood.com",
                "www.banggood.com"
            ]
        },
        {
            "rule": "fuarden\\.pro\\/engage\\/",
            "cookies": 0,
            "fingerprinting": 0,
            "subdomains": [],
            "apis": {},
            "sites": 3,
            "prevalence": 0.0000204,
            "cnames": [],
            "responseHashes": [
                "e3b0c44298fc1c149afbf4c8996fb92427ae41e4649b934ca495991b7852b855"
            ],
            "type": "Fetch",
            "firstPartyCookies": {},
            "firstPartyCookiesSent": {},
            "exampleSites": [
                "banggood.com",
                "usa.banggood.com",
                "www.banggood.com"
            ]
        }
    ],
    "categories": [],
    "performance": {},
    "cookies": 0.0000204,
    "topInitiators": [
        {
            "domain": "omguk.com",
            "prevalence": 0.5
        },
        {
            "domain": "sentry-cdn.com",
            "prevalence": 0.5
        }
    ],
    "types": {
        "Script": 3,
        "Fetch": 3
    },
    "nameservers": [
        "ns3.digitalocean.com",
        "ns2.digitalocean.com",
        "ns1.digitalocean.com"
    ]
}