{
    "domain": "ninetailed.co",
    "owner": {},
    "source": [
        "DuckDuckGo-US"
    ],
    "prevalence": 0.000075,
    "sites": 11,
    "subdomains": [
        "experience"
    ],
    "cnames": [],
    "fingerprinting": 0,
    "resources": [
        {
            "rule": "ninetailed\\.co\\/v2\\/organizations\\/1ddf955f-cfd8-4fed-b4aa-4569fde3ec09\\/environments\\/main\\/profiles",
            "cookies": 0,
            "fingerprinting": 0,
            "subdomains": [
                "experience"
            ],
            "apis": {},
            "sites": 2,
            "prevalence": 0.0000136,
            "cnames": [],
            "responseHashes": [
                "a5a70d3e60b9b713ce7edcf521ba96abeac6dc7f9cd3393eada8656554817c4a"
            ],
            "type": "Fetch",
            "firstPartyCookies": {},
            "firstPartyCookiesSent": {},
            "exampleSites": [
                "heinz.com",
                "www.heinz.com"
            ]
        },
        {
            "rule": "ninetailed\\.co\\/v2\\/organizations\\/1ddf955f-cfd8-4fed-b4aa-4569fde3ec09\\/environments\\/main\\/profiles\\/babeea7b0731ce410d1ef019601867eae40230c8ca3830229ac0dedfc0b45987",
            "cookies": 0,
            "fingerprinting": 0,
            "subdomains": [
                "experience"
            ],
            "apis": {},
            "sites": 2,
            "prevalence": 0.0000136,
            "cnames": [],
            "responseHashes": [
                "37adcef75a3078e9e1fb7beb021a63f8bd9e33c6704022fc43a9795db9a62989"
            ],
            "type": "Fetch",
            "firstPartyCookies": {},
            "firstPartyCookiesSent": {},
            "exampleSites": [
                "heinz.com",
                "www.heinz.com"
            ]
        },
        {
            "rule": "ninetailed\\.co\\/v2\\/organizations\\/1ddf955f-cfd8-4fed-b4aa-4569fde3ec09\\/environments\\/main\\/profiles\\/b86c9b5967921978f406eeaeffbd793fb2abc7ebd824b8799c3ff5aecbb52a1c",
            "cookies": 0,
            "fingerprinting": 0,
            "subdomains": [
                "experience"
            ],
            "apis": {},
            "sites": 2,
            "prevalence": 0.0000136,
            "cnames": [],
            "responseHashes": [
                "39646826c44e4d712a1f848ae444d93255232798efc28db365599aedcd0167ad"
            ],
            "type": "Fetch",
            "firstPartyCookies": {},
            "firstPartyCookiesSent": {},
            "exampleSites": [
                "heinz.com",
                "www.heinz.com"
            ]
        },
        {
            "rule": "ninetailed\\.co\\/v2\\/organizations\\/b65ca1df-31e9-47a6-b441-c992e8ecb2d0\\/environments\\/main\\/profiles",
            "cookies": 0,
            "fingerprinting": 0,
            "subdomains": [
                "experience"
            ],
            "apis": {},
            "sites": 2,
            "prevalence": 0.0000136,
            "cnames": [],
            "responseHashes": [
                "a08cb33a1e6bc9bc27e351a1e810bd2406119b6cf216c916631a347f41e0f82a"
            ],
            "type": "Fetch",
            "firstPartyCookies": {},
            "firstPartyCookiesSent": {},
            "exampleSites": [
                "tile.com",
                "www.tile.com"
            ]
        }
    ],
    "categories": [],
    "performance": {},
    "cookies": 0,
    "topInitiators": [
        {
            "domain": "first party",
            "prevalence": 1
        }
    ],
    "types": {
        "Fetch": 8
    },
    "nameservers": [
        "frank.ns.cloudflare.com",
        "jill.ns.cloudflare.com"
    ]
}