{
    "domain": "solutionshindsight.net",
    "owner": {},
    "source": [
        "DuckDuckGo-US"
    ],
    "prevalence": 0.000415,
    "sites": 61,
    "subdomains": [
        "static",
        "funes",
        "api2"
    ],
    "cnames": [],
    "fingerprinting": 1,
    "resources": [
        {
            "rule": "solutionshindsight\\.net\\/teju-webclient\\/entityTagging\\.min\\.js",
            "cookies": 0,
            "fingerprinting": 1,
            "subdomains": [
                "static"
            ],
            "apis": {
                "Screen.prototype.width": 12,
                "Navigator.prototype.userAgent": 12,
                "Date.prototype.getTime": 12
            },
            "sites": 12,
            "prevalence": 0.0000817,
            "cnames": [],
            "responseHashes": [
                "1608fd45e616cad7fc0e9f51eee566e5f46725b0de83c4e09f4ad689680ccf80"
            ],
            "type": "Script",
            "firstPartyCookies": {},
            "firstPartyCookiesSent": {},
            "exampleSites": [
                "blabbermouth.net",
                "countryrebel.com",
                "loudwire.com",
                "societyofrock.com",
                "tasteofcountry.com",
                "theboot.com",
                "top40weekly.com",
                "tvshowpilot.com",
                "ultimateclassicrock.com",
                "www.brooklynvegan.com",
                "www.metalsucks.net",
                "www.nashvillescene.com"
            ]
        },
        {
            "rule": "solutionshindsight\\.net\\/events\\/_bulk",
            "cookies": 0,
            "fingerprinting": 0,
            "subdomains": [
                "funes"
            ],
            "apis": {},
            "sites": 28,
            "prevalence": 0.000191,
            "cnames": [],
            "responseHashes": [],
            "type": "Preflight",
            "firstPartyCookies": {},
            "firstPartyCookiesSent": {},
            "exampleSites": [
                "blabbermouth.net",
                "nj1015.com",
                "www.wlsam.com",
                "top40weekly.com",
                "wpst.com",
                "countryrebel.com",
                "www.brooklynvegan.com",
                "loudwire.com",
                "www.marklevinshow.com",
                "societyofrock.com",
                "www.metalsucks.net",
                "www.altpress.com",
                "ndnation.com",
                "www.wmal.com",
                "metsmerizedonline.com",
                "www.nashvillescene.com",
                "tasteofcountry.com",
                "www.elcomercio.com",
                "www.ewrestlingnews.com",
                "theboot.com"
            ]
        },
        {
            "rule": "solutionshindsight\\.net\\/events\\/_bulk",
            "cookies": 0,
            "fingerprinting": 0,
            "subdomains": [
                "funes"
            ],
            "apis": {},
            "sites": 28,
            "prevalence": 0.000191,
            "cnames": [],
            "responseHashes": [
                "fe21151c36a8d466ee65dac37d6c6c897a701ed108e7116bbad85d41c3b0bec3",
                "a5bf03751888c27c7b457555abc51a32d572e47cf987fea6149c428263896f0e",
                "1dd2ab8854ad859c04623960de79057f34ae3c461089e24b5e2d51483b2a04a2",
                "aa5fcf91b062a6c68b76d8856a5fc6c979764261c655e05a2a55cddded8fd239",
                "b94007514728ae456f1b505db68c7e7b36d1b596f0e9f8236caec19cea07af7d",
                "8cd450a3873e8cdf0e91ce487d97c97854ab8f56412d87a49cce4d4ca2457a3b",
                "136e738b875a99bcd9de0d86a108d1e0019fbefa457755c227db3df4d0bf8d5b",
                "1147e538d86dff46042a81d558198816e0d885696947949a8ae4730201077651",
                "75c8e3dae73c2c5ad374fb4d0bc5ff3ae8867b7dc483429277839425de709523",
                "d42343b3365881c67b71f7657e0381e081e16f0e5d7d2070519f1d876aaedd4d",
                "e2761f62a8947c99a4f6e418c82f0acf7a8e052cbe616c69637673c9c6b6b1a2",
                "2a7f800f1d8c1381fcbb617d898ce1acc5754714ce87b256099deda208f9adc8",
                "6a82bda0ad9f6c1a3b2b6edc89710ed8200b341e8c061a98c3044bcfc539fac9",
                "22b8dd9368b2721bcb08321c3480952e80a80dcfa6dc2fe2ee3ee469bbce8e22",
                "8c762e3d0c71f1c2f85dd4c19c9774e193d66f4c388f9a3e25a4da72e1141e7f",
                "7360d72e79d63aae7944682dcd790263fbd3c1e8ed1e8906b9f92d650552b05c",
                "d767a665fa4adb1c9cb2f8e9047e0c0e942b89dba1cda90100436d1f285022c9",
                "5ffefb092d7417ff97262826c327a49c398318fee4c04153751f61f844df16da",
                "00b0900e9888ce52c193bc76c314f66f5dbbcc0d8d03d64acadcf146d6046005",
                "d8d8cd78c83b73aafb307f8e02e58f184f3527e4708c50ee23b6c17f2ae2e746",
                "9406d76cdb307a5c3da773cba6dfb4fc1510bf4462c6a95052d467afb6c8794e",
                "099df5e243f8321cc3dd2d468add8b55ebcd2be3c2117f44f08e082f76deda21"
            ],
            "type": "Fetch",
            "firstPartyCookies": {},
            "firstPartyCookiesSent": {},
            "exampleSites": [
                "societyofrock.com",
                "www.altpress.com",
                "www.huskermax.com",
                "www.hardreset.info",
                "wpst.com",
                "www.ewrestlingnews.com",
                "golangdocs.com",
                "www.brooklynvegan.com",
                "www.wideopeneats.com",
                "loudwire.com",
                "ultimateclassicrock.com",
                "tasteofcountry.com",
                "top40weekly.com",
                "www.metalsucks.net",
                "blabbermouth.net",
                "www.kabc.com",
                "theboot.com",
                "www.lowcarbchef.nl",
                "countryrebel.com",
                "www.nashvillescene.com"
            ]
        },
        {
            "rule": "solutionshindsight\\.net\\/v1\\/ads",
            "cookies": 0,
            "fingerprinting": 0,
            "subdomains": [
                "api2"
            ],
            "apis": {},
            "sites": 10,
            "prevalence": 0.0000681,
            "cnames": [],
            "responseHashes": [
                "d01472235f3156e5b650eec58e8b053ab8579e2d1c988809db34b10efe915ae0",
                "3ed39665aa80fd76e660f20234640eed30be5cecbd77f92d48661cc629a53414",
                "bc5a644d39988fa0be21dd61ac9cfc64148fe929bd023b8d1f3bee4cc85b217e",
                "85521b65b160b4a88a8b8093946f9af6ac742476301dad952d91a9ee00ef62aa",
                "3295975d6009fcb8fcfa4d99e7602599d21dfba126320c3fcfc07bbf1e2d241d",
                "7aabcb5cc369f95d8977c7551310e10114d707e4fb2776f8a061fb6e942321bc"
            ],
            "type": "XHR",
            "firstPartyCookies": {},
            "firstPartyCookiesSent": {
                "lotame_domain_check": 0.00002042275094455223
            },
            "exampleSites": [
                "blabbermouth.net",
                "countryrebel.com",
                "loudwire.com",
                "societyofrock.com",
                "theboot.com",
                "top40weekly.com",
                "ultimateclassicrock.com",
                "www.brooklynvegan.com",
                "www.metalsucks.net",
                "www.nashvillescene.com"
            ]
        },
        {
            "rule": "solutionshindsight\\.net\\/hindsightipads\\/hindsightipads\\.min\\.js",
            "cookies": 0,
            "fingerprinting": 1,
            "subdomains": [
                "static"
            ],
            "apis": {
                "Date.prototype.getTime": 5,
                "Screen.prototype.width": 5,
                "Navigator.prototype.userAgent": 5
            },
            "sites": 5,
            "prevalence": 0.000034,
            "cnames": [],
            "responseHashes": [
                "e03e20a6cece2067e3dc9f7c3af88fe2df7c5e863bcde70f8d44cd77642f4bde"
            ],
            "type": "Script",
            "firstPartyCookies": {},
            "firstPartyCookiesSent": {},
            "exampleSites": [
                "cyclonefanatic.com",
                "forum.killerfrogs.com",
                "forum.uhnd.com",
                "metsmerizedonline.com",
                "ndnation.com"
            ]
        },
        {
            "rule": "solutionshindsight\\.net\\/teju-webclient\\/wp-banners\\.js",
            "cookies": 0,
            "fingerprinting": 0,
            "subdomains": [
                "static"
            ],
            "apis": {},
            "sites": 23,
            "prevalence": 0.000157,
            "cnames": [],
            "responseHashes": [
                "24015e87dffbcb2aff83c109e1bb04da370a79c6a2a54b008dcf4a501db4473a"
            ],
            "type": "Script",
            "firstPartyCookies": {},
            "firstPartyCookiesSent": {},
            "exampleSites": [
                "www.kabc.com",
                "ndnation.com",
                "tasteofcountry.com",
                "www.brooklynvegan.com",
                "www.newcastleherald.com.au",
                "nj1015.com",
                "cyclonefanatic.com",
                "www.elcomercio.com",
                "www.wideopenpets.com",
                "wpst.com",
                "www.wmal.com",
                "www.marklevinshow.com",
                "metsmerizedonline.com",
                "ultimateclassicrock.com",
                "www.wlsam.com",
                "gon.com",
                "theboot.com",
                "www.ewrestlingnews.com",
                "loudwire.com",
                "www.altpress.com"
            ]
        },
        {
            "rule": "solutionshindsight\\.net\\/teju-webclient\\/teju-webclient\\.min\\.js",
            "cookies": 0,
            "fingerprinting": 1,
            "subdomains": [
                "static"
            ],
            "apis": {
                "Date.prototype.getTime": 22,
                "Screen.prototype.width": 21,
                "Navigator.prototype.userAgent": 22
            },
            "sites": 22,
            "prevalence": 0.00015,
            "cnames": [],
            "responseHashes": [
                "e03e20a6cece2067e3dc9f7c3af88fe2df7c5e863bcde70f8d44cd77642f4bde"
            ],
            "type": "Script",
            "firstPartyCookies": {},
            "firstPartyCookiesSent": {},
            "exampleSites": [
                "wjon.com",
                "www.altpress.com",
                "www.huskermax.com",
                "tasteofcountry.com",
                "loudwire.com",
                "www.wmal.com",
                "www.marklevinshow.com",
                "ultimateclassicrock.com",
                "wpst.com",
                "tuscaloosathread.com",
                "www.kabc.com",
                "www.ewrestlingnews.com",
                "kpq.com",
                "forum.gon.com",
                "wnbf.com",
                "newstalk1290.com",
                "gon.com",
                "nj1015.com",
                "www.wlsam.com",
                "theboot.com"
            ]
        },
        {
            "rule": "solutionshindsight\\.net\\/assets\\/Zm9ydW0uZ29uLmNvbQ==",
            "cookies": 0,
            "fingerprinting": 0,
            "subdomains": [
                "static"
            ],
            "apis": {},
            "sites": 2,
            "prevalence": 0.0000136,
            "cnames": [],
            "responseHashes": [
                "948ff5b2bd274d7d869805621ef8ec9dfd77abe2d151e6b6633c1915dc5277a5"
            ],
            "type": "Fetch",
            "firstPartyCookies": {},
            "firstPartyCookiesSent": {},
            "exampleSites": [
                "gon.com",
                "forum.gon.com"
            ]
        },
        {
            "rule": "solutionshindsight\\.net\\/teju-webclient\\/networks\\/adpushup_related_content\\.min\\.js",
            "cookies": 0,
            "fingerprinting": 1,
            "subdomains": [
                "static"
            ],
            "apis": {
                "Date.prototype.getTime": 3,
                "Screen.prototype.width": 3,
                "Navigator.prototype.userAgent": 3
            },
            "sites": 3,
            "prevalence": 0.0000204,
            "cnames": [],
            "responseHashes": [
                "f5e88ed3c713f5e2f44219d2be7ede8ca98a6d73e3182acbeffd5161cde131c2"
            ],
            "type": "Script",
            "firstPartyCookies": {},
            "firstPartyCookiesSent": {},
            "exampleSites": [
                "golangdocs.com",
                "www.hardreset.info",
                "www.lowcarbchef.nl"
            ]
        },
        {
            "rule": "solutionshindsight\\.net\\/v1\\/articles",
            "cookies": 0,
            "fingerprinting": 0,
            "subdomains": [
                "api2"
            ],
            "apis": {},
            "sites": 6,
            "prevalence": 0.0000408,
            "cnames": [],
            "responseHashes": [
                "7af6b55379e8f96457452ea80aafa0c8f397420f0675a029360bd9ef10394b1b"
            ],
            "type": "Fetch",
            "firstPartyCookies": {},
            "firstPartyCookiesSent": {
                "lotame_domain_check": 0.000013615167296368154
            },
            "exampleSites": [
                "loudwire.com",
                "tasteofcountry.com",
                "www.kabc.com",
                "www.musclecarsandtrucks.com",
                "www.wlsam.com",
                "www.wmal.com"
            ]
        },
        {
            "rule": "solutionshindsight\\.net\\/assets\\/d3d3LmJyb29rbHludmVnYW4uY29t",
            "cookies": 0,
            "fingerprinting": 0,
            "subdomains": [
                "static"
            ],
            "apis": {},
            "sites": 2,
            "prevalence": 0.0000136,
            "cnames": [],
            "responseHashes": [
                "0f68deaff717483a554a0958a044f0137d7c17fef52e35b4cd2c8c58160fed28"
            ],
            "type": "Fetch",
            "firstPartyCookies": {},
            "firstPartyCookiesSent": {},
            "exampleSites": [
                "brooklynvegan.com",
                "www.brooklynvegan.com"
            ]
        },
        {
            "rule": "solutionshindsight\\.net\\/teju-webclient\\/hindsight-webclient\\.min\\.js",
            "cookies": 0,
            "fingerprinting": 1,
            "subdomains": [
                "static"
            ],
            "apis": {
                "Date.prototype.getTime": 5,
                "Screen.prototype.width": 5,
                "Navigator.prototype.userAgent": 5
            },
            "sites": 5,
            "prevalence": 0.000034,
            "cnames": [],
            "responseHashes": [
                "e03e20a6cece2067e3dc9f7c3af88fe2df7c5e863bcde70f8d44cd77642f4bde"
            ],
            "type": "Script",
            "firstPartyCookies": {},
            "firstPartyCookiesSent": {},
            "exampleSites": [
                "canberratimes.com.au",
                "www.elcomercio.com",
                "www.newcastleherald.com.au",
                "www.wideopeneats.com",
                "www.wideopenpets.com"
            ]
        },
        {
            "rule": "solutionshindsight\\.net\\/assets\\/d3d3Lmh1c2tlcm1heC5jb20=",
            "cookies": 0,
            "fingerprinting": 0,
            "subdomains": [
                "static"
            ],
            "apis": {},
            "sites": 2,
            "prevalence": 0.0000136,
            "cnames": [],
            "responseHashes": [
                "3d40959b90d8a4f243ced3f7c5ccce5f850a9baa868f01df6528e0f3929b4c87"
            ],
            "type": "Fetch",
            "firstPartyCookies": {},
            "firstPartyCookiesSent": {},
            "exampleSites": [
                "huskermax.com",
                "www.huskermax.com"
            ]
        },
        {
            "rule": "solutionshindsight\\.net\\/publisher-logos\\/Hinodi_standard\\.svg",
            "cookies": 0,
            "fingerprinting": 0,
            "subdomains": [
                "static"
            ],
            "apis": {},
            "sites": 2,
            "prevalence": 0.0000136,
            "cnames": [],
            "responseHashes": [
                "2c9abe5b1f986e197eaf6c29bd2d354d1d7433f75790257bbb2a951e9ba2ec4b"
            ],
            "type": "Image",
            "firstPartyCookies": {},
            "firstPartyCookiesSent": {},
            "exampleSites": [
                "huskermax.com",
                "www.huskermax.com"
            ]
        },
        {
            "rule": "solutionshindsight\\.net\\/assets\\/d3d3LndpZGVvcGVuZWF0cy5jb20=",
            "cookies": 0,
            "fingerprinting": 0,
            "subdomains": [
                "static"
            ],
            "apis": {},
            "sites": 2,
            "prevalence": 0.0000136,
            "cnames": [],
            "responseHashes": [
                "ebf2ba015b55c03cea4c4ed1b5887a0703a84c450488d5fc22295b92b6077f93"
            ],
            "type": "Fetch",
            "firstPartyCookies": {},
            "firstPartyCookiesSent": {},
            "exampleSites": [
                "wideopeneats.com",
                "www.wideopeneats.com"
            ]
        },
        {
            "rule": "solutionshindsight\\.net\\/assets\\/d3d3LndpZGVvcGVucGV0cy5jb20=",
            "cookies": 0,
            "fingerprinting": 0,
            "subdomains": [
                "static"
            ],
            "apis": {},
            "sites": 2,
            "prevalence": 0.0000136,
            "cnames": [],
            "responseHashes": [
                "e11ec97027cf1b322c1ddc696c9d10a0fe2bb60a61a83fbf3abfa329d273f540"
            ],
            "type": "Fetch",
            "firstPartyCookies": {},
            "firstPartyCookiesSent": {},
            "exampleSites": [
                "wideopenpets.com",
                "www.wideopenpets.com"
            ]
        }
    ],
    "categories": [],
    "performance": {},
    "cookies": 0,
    "topInitiators": [
        {
            "domain": "clickfuse.com",
            "prevalence": 0.20155038759689922
        },
        {
            "domain": "dbejeqv8nk3po.cloudfront.net",
            "prevalence": 0.16279069767441862
        },
        {
            "domain": "d1180od816jent.cloudfront.net",
            "prevalence": 0.11627906976744186
        },
        {
            "domain": "doi3unldljdx6.cloudfront.net",
            "prevalence": 0.11627906976744186
        },
        {
            "domain": "storage.googleapis.com",
            "prevalence": 0.09302325581395349
        },
        {
            "domain": "tunefindforfans.com",
            "prevalence": 0.06201550387596899
        },
        {
            "domain": "d3c6l876mn6xxv.cloudfront.net",
            "prevalence": 0.06201550387596899
        },
        {
            "domain": "dfm7wh2x5l4za.cloudfront.net",
            "prevalence": 0.046511627906976744
        },
        {
            "domain": "adpushup.com",
            "prevalence": 0.031007751937984496
        },
        {
            "domain": "first party",
            "prevalence": 0.031007751937984496
        }
    ],
    "types": {
        "Script": 70,
        "Preflight": 28,
        "Fetch": 44,
        "XHR": 10,
        "Image": 2
    },
    "nameservers": [
        "ns-99.awsdns-12.com",
        "ns-1532.awsdns-63.org",
        "ns-1742.awsdns-25.co.uk",
        "ns-666.awsdns-19.net"
    ]
}